[{"id":"page-/","title":"Computational Arithmetic Geometry","content":"AG Computational Arithmetic Geometry Prof. Dr. Gebhard BÃ¶ckle .hero-header { position: relative; width: 100%; height: 400px; overflow: hidden; border-radius: 12px; box-shadow: 0 8px 32px rgba(0,0,0,0.15); margin-bottom: 3rem; } .hero-image { width: 100%; height: 100%; object-fit: cover; object-position: center; } .hero-overlay { position: absolute; top: 0; left: 0; right: 0; bottom: 0; background: linear-gradient(135deg, rgba(0,0,0,0.7) 0%, rgba(0,0,0,0.4) 50%, rgba(0,0,0,0.2) 100%); display: flex; align-items: center; justify-content: center; } .hero-content { text-align: center; color: white; padding: 2rem; } .hero-title { font-size: 3rem; font-weight: 700; margin-bottom: 0.5rem; text-shadow: 2px 2px 4px rgba(0,0,0,0.8); } .hero-subtitle { font-size: 1.5rem; font-weight: 400; margin: 0; text-shadow: 1px 1px 2px rgba(0,0,0,0.8); } @media (max-width: 768px) { .hero-header { height: 300px; } .hero-title { font-size: 2rem; } .hero-subtitle { font-size: 1.2rem; } } / Content Sections Styles / .content-sections { max-width: 1200px; margin: 0 auto; } .content-section { margin-bottom: 3rem; padding: 2rem; background: var(--bg-primary); border-radius: var(--radius-lg); border: 1px solid var(--border-color); box-shadow: var(--shadow-sm); transition: all var(--transition-base); } .content-section:hover { box-shadow: var(--shadow-md); transform: translateY(-2px); } .section-header { display: flex; align-items: center; gap: 1rem; margin-bottom: 1.5rem; padding-bottom: 1rem; border-bottom: 2px solid var(--primary); } .section-icon { width: 50px; height: 50px; background: linear-gradient(135deg, var(--primary) 0%, var(--heidelberg-red) 100%); color: white; border-radius: 50%; display: flex; align-items: center; justify-content: center; font-size: 1.25rem; box-shadow: var(--shadow-sm); } .section-header h3 { color: var(--text-primary); font-size: 1.8rem; font-weight: 600; margin: 0; } .content-section p { color: var(--text-secondary); font-size: 1.1rem; line-height: 1.7; margin-bottom: 1rem; } .cta-buttons { display: flex; gap: 1rem; flex-wrap: wrap; margin-top: 1.5rem; } .cta-buttons .btn { padding: 0.75rem 1.5rem; font-weight: 500; border-radius: var(--radius-md); transition: all var(--transition-base); } .cta-buttons .btn:hover { transform: translateY(-2px); box-shadow: var(--shadow-md); } .contact-section { background: linear-gradient(135deg, var(--bg-primary) 0%, var(--bg-secondary) 100%); border: 2px solid var(--primary); } .contact-info { background: var(--bg-secondary); padding: 1.5rem; border-radius: var(--radius-md); border: 1px solid var(--border-color); } .contact-info p { margin-bottom: 0.5rem; font-size: 1rem; } .contact-info a { color: var(--primary); text-decoration: none; font-weight: 500; } .contact-info a:hover { text-decoration: underline; } / Responsive adjustments for content sections / @media (max-width: 768px) { .content-section { padding: 1.5rem; } .section-header { flex-direction: column; text-align: center; gap: 0.5rem; } .section-icon { width: 40px; height: 40px; font-size: 1rem; } .section-header h3 { font-size: 1.5rem; } .cta-buttons { flex-direction: column; } .cta-buttons .btn { width: 100%; text-align: center; } } @media (max-width: 480px) { .content-section { padding: 1rem; } .contact-info { padding: 1rem; } } About Our Research Group This is the website of the research group \"computational arithmetic geometry\" at the Interdisciplinary Center for Scientific Computing (IWR) in Heidelberg. Research Focus Within algebraic number theory and arithmetic geometry, the focus of the research group is on Galois representations, their relations to modular forms and elliptic curves, their deformation theory etc., as well as on some aspects of function field arithmetic such as L-functions and Drinfeld modular forms. Our Methods To tackle problems in the themes described above, we apply a broad range of methods. On one hand we pursue these questions by purely theoretical methods. On the other, we use computer algebra to carry out experiments that help us gather examples for the theory or to solve particular questions that arise from the theory. Some members of our group have also developed routines on top of existing computer algebra packages. Learn More A more detailed survey of our activities can be found in the research section and in the publications of our members. Research Areas Publications Our Team Contact Us Email: arithgeo@iwr.uni-heidelberg.de Location: Interdisciplinary Center for Scientific Computing (IWR), University of Heidelberg  Computational Arithmetic Geometry","url":"/","category":"page","description":"","tags":"","date":null,"layout":"page"},{"id":"page-/assets/css/main.css","title":"main.scss","content":"@use \"forward\" as ; // Enhanced High-Contrast Academic Theme // Optimized for performance and accessibility // CSS Custom Properties for enhanced functionality :root { // Spacing utilities --space-xs: 0.25rem; --space-sm: 0.5rem; --space-md: 1rem; --space-lg: 1.5rem; --space-xl: 2rem; --space-2xl: 2.5rem; // Border radius utilities --radius-sm: 0.25rem; --radius-md: 0.375rem; --radius-lg: 0.5rem; --radius-xl: 0.75rem; --radius-2xl: 1rem; --radius-full: 9999px; // Typography scale --text-xs: 0.75rem; --text-sm: 0.875rem; --text-base: 1rem; --text-lg: 1.125rem; --text-xl: 1.25rem; --text-2xl: 1.5rem; --text-3xl: 1.875rem; --text-4xl: 2.25rem; // Z-index layers --z-dropdown: 1000; --z-sticky: 1020; --z-fixed: 1030; --z-modal: 1050; --z-tooltip: 1070; } // Enhanced body and html styling html { scroll-behavior: smooth; -webkit-font-smoothing: antialiased; -moz-osx-font-smoothing: grayscale; font-size: 16px; line-height: 1.6; } body { margin: 0; padding: 0; background-color: var(--bg-primary) !important; color: var(--text-primary) !important; font-family: 'Inter', -apple-system, BlinkMacSystemFont, 'Segoe UI', 'Roboto', 'Oxygen', 'Ubuntu', 'Cantarell', 'Fira Sans', 'Droid Sans', 'Helvetica Neue', sans-serif; line-height: 1.6; -webkit-font-smoothing: antialiased; -moz-osx-font-smoothing: grayscale; transition: background-color 0.3s ease, color 0.3s ease; overflow-x: hidden; } // Typography enhancements h1, h2, h3, h4, h5, h6 { color: var(--text-primary) !important; font-weight: 600; margin: 0.5em 0; line-height: 1.2; } h1 { font-size: var(--text-4xl); } h2 { font-size: var(--text-3xl); } h3 { font-size: var(--text-2xl); } h4 { font-size: var(--text-xl); } h5 { font-size: var(--text-lg); } h6 { font-size: var(--text-base); } p, span, li, td, th, label, strong, em { color: var(--text-primary) !important; } small, .small { font-size: var(--text-sm); color: var(--text-muted) !important; } // Enhanced link styling a { color: var(--link-color) !important; text-decoration: none; transition: all 0.2s ease; &:hover, &:focus { color: var(--link-hover) !important; text-decoration: underline; } } // Dark mode link adjustments for better visibility [data-theme=\"dark\"] a, body.dark-mode a, html.dark-mode a { color: ff6b6b !important; } [data-theme=\"dark\"] a:hover, [data-theme=\"dark\"] a:focus, body.dark-mode a:hover, body.dark-mode a:focus, html.dark-mode a:hover, html.dark-mode a:focus { color: ff5252 !important; } // Enhanced dark mode styling for all elements [data-theme=\"dark\"], body.dark-mode, html.dark-mode { // Force dark backgrounds background-color: $black-color !important; // Enhanced dark mode for all containers .container, .container-fluid, .row, .col, main, section, article, .content, .page-content { background-color: $black-color !important; color: $white-color !important; } // Enhanced dark mode for cards .card { background-color: $gray-900 !important; border-color: $gray-700 !important; color: $white-color !important; } .card-header { background-color: $gray-800 !important; border-color: $gray-700 !important; color: $white-color !important; } .card-body { background-color: $gray-900 !important; color: $white-color !important; } .card-footer { background-color: $gray-800 !important; border-color: $gray-700 !important; color: $white-color !important; } // Enhanced dark mode for forms .form-control, .form-select, input, textarea, select { background-color: $gray-900 !important; border-color: $gray-700 !important; color: $white-color !important; } .form-control:focus, .form-select:focus, input:focus, textarea:focus, select:focus { background-color: $gray-900 !important; border-color: $red-400 !important; color: $white-color !important; box-shadow: 0 0 0 3px rgba(248, 113, 113, 0.2) !important; } // Enhanced dark mode for tables table { background-color: $gray-900 !important; color: $white-color !important; } thead th { background-color: $gray-800 !important; border-color: $gray-700 !important; color: $white-color !important; } tbody tr { border-color: $gray-700 !important; } tbody tr:hover { background-color: $gray-800 !important; } tbody tr:nth-child(even) { background-color: $gray-800 !important; } tbody tr:nth-child(even):hover { background-color: $gray-700 !important; } tbody td { color: $white-color !important; } // Enhanced dark mode for buttons .btn-secondary { background-color: $gray-700 !important; border-color: $gray-600 !important; color: $white-color !important; } .btn-secondary:hover, .btn-secondary:focus { background-color: $gray-600 !important; border-color: $gray-500 !important; color: $white-color !important; } // Enhanced dark mode for dropdowns .dropdown-menu { background-color: $gray-900 !important; border-color: $gray-700 !important; color: $white-color !important; } .dropdown-item { color: $white-color !important; } .dropdown-item:hover, .dropdown-item:focus { background-color: $gray-800 !important; color: $white-color !important; } // Enhanced dark mode for search .search-input { background-color: $gray-900 !important; border-color: $gray-700 !important; color: $white-color !important; } .search-input:focus { background-color: $gray-900 !important; border-color: $red-400 !important; color: $white-color !important; } .search-results-container { background-color: $gray-900 !important; border-color: $gray-700 !important; color: $white-color !important; } .search-result-item { border-color: $gray-700 !important; color: $white-color !important; } .search-result-item:hover, .search-result-item.active { background-color: $gray-800 !important; color: $white-color !important; } .search-result-title { color: $white-color !important; } .search-result-content { color: $gray-300 !important; } .search-result-url { color: $gray-400 !important; } .search-result-category { background-color: $gray-700 !important; color: $gray-400 !important; } } // Main content areas with proper backgrounds main, .container, .container-fluid, .hero-section, section, article, .content { background-color: var(--bg-primary) !important; color: var(--text-primary) !important; } // Enhanced card styling .card { background: var(--bg-primary) !important; color: var(--text-primary) !important; border: 1px solid var(--border-color); border-radius: var(--radius-lg); box-shadow: var(--shadow-sm); transition: all var(--transition-base); overflow: hidden; &:hover { box-shadow: var(--shadow-md); transform: translateY(-2px); } } .card-header { background: var(--bg-secondary) !important; color: var(--text-primary) !important; border-bottom: 1px solid var(--border-color); padding: var(--space-md) var(--space-lg); font-weight: 600; } .card-body { background: var(--bg-primary) !important; color: var(--text-primary) !important; padding: var(--space-lg); } .card-footer { background: var(--bg-secondary) !important; color: var(--text-primary) !important; border-top: 1px solid var(--border-color); padding: var(--space-md) var(--space-lg); } // Enhanced button styling .btn { font-weight: 500; border-radius: var(--radius-lg); transition: all var(--transition-base); border: 1px solid transparent; padding: 0.5rem 1rem; font-size: var(--text-base); line-height: 1.5; cursor: pointer; min-height: 44px; // Accessibility: minimum touch target size &:focus { outline: 2px solid var(--primary); outline-offset: 2px; } } .btn-primary { background: var(--primary) !important; color: var(--primary-text) !important; border-color: var(--primary) !important; &:hover, &:focus { background: var(--primary-hover) !important; border-color: var(--primary-hover) !important; color: var(--primary-text) !important; transform: translateY(-1px); box-shadow: var(--shadow-md); } } .btn-secondary { background: var(--bg-secondary) !important; color: var(--text-primary) !important; border-color: var(--border-color) !important; &:hover, &:focus { background: var(--bg-muted) !important; color: var(--text-primary) !important; border-color: var(--border-dark) !important; } } .btn-outline-primary { background: transparent !important; color: var(--primary) !important; border-color: var(--primary) !important; &:hover, &:focus { background: var(--primary) !important; color: var(--primary-text) !important; border-color: var(--primary) !important; } } .btn-outline-light { background: rgba(255, 255, 255, 0.1) !important; color: var(--white) !important; border-color: rgba(255, 255, 255, 0.3) !important; &:hover, &:focus { background: rgba(255, 255, 255, 0.2) !important; color: var(--white) !important; border-color: rgba(255, 255, 255, 0.5) !important; } } // Enhanced form styling .form-control, .form-select, input[type=\"text\"], input[type=\"email\"], input[type=\"password\"], input[type=\"search\"], input[type=\"url\"], input[type=\"tel\"], input[type=\"number\"], textarea { background: var(--bg-primary) !important; color: var(--text-primary) !important; border: 2px solid var(--border-color) !important; border-radius: var(--radius-md); padding: 0.5rem 0.75rem; transition: all var(--transition-fast); font-size: var(--text-base); min-height: 44px; // Accessibility: minimum touch target size &:focus { background: var(--bg-primary) !important; color: var(--text-primary) !important; border-color: var(--primary) !important; box-shadow: 0 0 0 3px rgba(194, 32, 50, 0.1) !important; outline: none; } &::placeholder { color: var(--text-muted) !important; opacity: 0.7; } } // Enhanced Search Bar Styling - Modern Design .search-container { position: relative; display: flex; align-items: center; background: rgba(255, 255, 255, 0.08); border: 1px solid rgba(255, 255, 255, 0.15); border-radius: 1rem; padding: 0.5rem; backdrop-filter: blur(10px); transition: all 0.3s cubic-bezier(0.4, 0, 0.2, 1); box-shadow: 0 4px 6px -1px rgba(0, 0, 0, 0.1), 0 2px 4px -1px rgba(0, 0, 0, 0.06); } .search-container:hover { background: rgba(255, 255, 255, 0.12); border-color: rgba(255, 255, 255, 0.25); transform: translateY(-1px); box-shadow: 0 10px 15px -3px rgba(0, 0, 0, 0.1), 0 4px 6px -2px rgba(0, 0, 0, 0.05); } .search-container:focus-within { background: rgba(255, 255, 255, 0.15); border-color: var(--primary); box-shadow: 0 0 0 3px rgba(220, 38, 38, 0.15), 0 10px 25px -5px rgba(0, 0, 0, 0.1); transform: translateY(-2px); } .search-container-center { flex: 1; justify-content: center; max-width: 450px; margin: 0 1.5rem; } // Enhanced search input wrapper .search-input-wrapper { position: relative; flex: 1; display: flex; align-items: center; } .search-input-icon { position: absolute; left: 1rem; color: rgba(255, 255, 255, 0.6); font-size: 1.1rem; z-index: 1; pointer-events: none; transition: color 0.2s ease; } .search-input { width: 100%; background: transparent; border: none; color: var(--white); font-size: 0.95rem; font-weight: 500; padding: 0.75rem 1rem 0.75rem 3rem; border-radius: 0.75rem; transition: all 0.2s ease; min-height: 48px; letter-spacing: 0.025em; } .search-input:focus { outline: none; background: rgba(255, 255, 255, 0.05); } .search-input:focus + .search-input-icon, .search-container:focus-within .search-input-icon { color: var(--primary); } .search-input::placeholder { color: rgba(255, 255, 255, 0.6); font-weight: 400; transition: color 0.2s ease; } .search-input:focus::placeholder { color: rgba(255, 255, 255, 0.4); } // Enhanced search toggle button .search-toggle-btn { display: flex; align-items: center; justify-content: center; width: 48px; height: 48px; border-radius: 0.75rem; transition: all 0.2s cubic-bezier(0.4, 0, 0.2, 1); background: rgba(255, 255, 255, 0.1); border: 1px solid rgba(255, 255, 255, 0.2); color: var(--white); cursor: pointer; position: relative; overflow: hidden; } .search-toggle-btn::before { content: ''; position: absolute; top: 0; left: 0; right: 0; bottom: 0; background: linear-gradient(135deg, rgba(255, 255, 255, 0.1), rgba(255, 255, 255, 0.05)); opacity: 0; transition: opacity 0.2s ease; } .search-toggle-btn:hover { background: rgba(255, 255, 255, 0.15); border-color: rgba(255, 255, 255, 0.3); transform: translateY(-1px) scale(1.02); box-shadow: 0 4px 12px rgba(0, 0, 0, 0.15); } .search-toggle-btn:hover::before { opacity: 1; } .search-toggle-btn:active { transform: translateY(0) scale(0.98); } .search-toggle-btn i { font-size: 1.1rem; position: relative; z-index: 1; transition: transform 0.2s ease; } .search-toggle-btn:hover i { transform: scale(1.1); } // Enhanced search results container - Bigger and better .search-results-container { display: none; position: absolute; top: calc(100% + 0.75rem); left: 0; width: 500px; background: var(--bg-primary); border: 1px solid var(--border-color); border-radius: 1rem; box-shadow: 0 25px 50px -12px rgba(0, 0, 0, 0.25), 0 0 0 1px rgba(255, 255, 255, 0.05); z-index: var(--z-dropdown); max-height: 600px; overflow: hidden; backdrop-filter: blur(20px); animation: searchResultsSlideIn 0.3s cubic-bezier(0.4, 0, 0.2, 1); } .search-results-container.show { display: block; } .search-results-container::before { content: ''; position: absolute; top: -8px; left: 20px; width: 16px; height: 16px; background: var(--bg-primary); border-left: 1px solid var(--border-color); border-top: 1px solid var(--border-color); transform: rotate(45deg); z-index: -1; } // Enhanced search result items - Bigger and more prominent .search-result-item { padding: 1.25rem 1.5rem; border-bottom: 1px solid var(--border-color); cursor: pointer; transition: all 0.2s cubic-bezier(0.4, 0, 0.2, 1); position: relative; min-height: 60px; background: var(--bg-primary); &:last-child { border-bottom: none; } &:hover, &.active { background: var(--bg-secondary); transform: translateX(6px); box-shadow: 0 8px 25px rgba(0, 0, 0, 0.15); } &:active { transform: translateX(3px) scale(0.98); } } .search-result-item::before { content: ''; position: absolute; left: 0; top: 0; bottom: 0; width: 3px; background: var(--primary); transform: scaleY(0); transition: transform 0.2s ease; } .search-result-item:hover::before, .search-result-item.active::before { transform: scaleY(1); } .search-result-header { display: flex; justify-content: space-between; align-items: flex-start; margin-bottom: 0.5rem; gap: 0.75rem; } .search-result-title { font-weight: 700; color: var(--text-primary); font-size: 1.1rem; line-height: 1.3; flex: 1; margin: 0; margin-bottom: 0.25rem; } .search-result-category { font-size: 0.7rem; color: var(--text-muted); background: var(--bg-tertiary); padding: 0.25rem 0.5rem; border-radius: 0.5rem; white-space: nowrap; font-weight: 500; text-transform: uppercase; letter-spacing: 0.05em; } .search-result-content { color: var(--text-secondary); font-size: 0.95rem; line-height: 1.5; margin-bottom: 0.75rem; display: -webkit-box; -webkit-line-clamp: 3; -webkit-box-orient: vertical; overflow: hidden; } .search-result-url { font-size: 0.75rem; color: var(--text-muted); font-family: var(--font-mono); opacity: 0.8; word-break: break-all; } // Enhanced empty state .search-empty-state { padding: 3rem 2rem; text-align: center; color: var(--text-muted); background: var(--bg-primary); } .search-empty-state i { font-size: 3rem; margin-bottom: 1rem; opacity: 0.4; color: var(--text-tertiary); } .search-empty-state p { margin-bottom: 0.5rem; font-weight: 500; font-size: 1rem; color: var(--text-secondary); } .search-empty-state small { font-size: 0.85rem; opacity: 0.7; color: var(--text-tertiary); } // Enhanced search term highlighting .search-result-item mark { background: linear-gradient(135deg, var(--primary), dc2626); color: var(--white); padding: 0.1rem 0.3rem; border-radius: 0.25rem; font-weight: 600; box-shadow: 0 1px 2px rgba(0, 0, 0, 0.1); } // Search animations @keyframes searchResultsSlideIn { from { opacity: 0; transform: translateY(-10px) scale(0.95); } to { opacity: 1; transform: translateY(0) scale(1); } } @keyframes searchInputFocus { from { transform: scale(1); } to { transform: scale(1.02); } } // Mobile search adjustments @media (max-width: 1199.98px) { .search-container-center { display: none !important; } } @media (max-width: 991.98px) { .search-container { width: 100%; margin: 0.75rem 0; gap: 0.5rem; } .search-input { font-size: 0.9rem; padding: 0.75rem 1rem; } .search-results-container { width: 100%; left: 0; right: 0; max-width: none; } .search-results-container::before { left: 50%; transform: translateX(-50%) rotate(45deg); } } @media (max-width: 576px) { .search-container { gap: 0.5rem; padding: 0.5rem; border-radius: 0.75rem; } .search-input { font-size: 0.85rem; padding: 0.75rem; min-height: 44px; } .search-toggle-btn { width: 44px; height: 44px; border-radius: 0.75rem; } .search-toggle-btn i { font-size: 1rem; } .search-result-item { padding: 1rem; } .search-result-title { font-size: 0.9rem; } .search-result-content { font-size: 0.8rem; } } // Dark mode enhancements [data-theme=\"dark\"] .search-container, body.dark-mode .search-container { background: rgba(0, 0, 0, 0.3); border-color: rgba(255, 255, 255, 0.1); } [data-theme=\"dark\"] .search-container:hover, body.dark-mode .search-container:hover { background: rgba(0, 0, 0, 0.4); border-color: rgba(255, 255, 255, 0.15); } [data-theme=\"dark\"] .search-container:focus-within, body.dark-mode .search-container:focus-within { background: rgba(0, 0, 0, 0.5); border-color: var(--primary); } [data-theme=\"dark\"] .search-toggle-btn, body.dark-mode .search-toggle-btn { background: rgba(255, 255, 255, 0.05); border-color: rgba(255, 255, 255, 0.1); } [data-theme=\"dark\"] .search-toggle-btn:hover, body.dark-mode .search-toggle-btn:hover { background: rgba(255, 255, 255, 0.1); border-color: rgba(255, 255, 255, 0.2); } / Table of Contents Styling / .toc-container { background: var(--bg-secondary); padding: 1rem 1.5rem; margin-bottom: 2rem; border-radius: var(--radius-lg); border: 1px solid var(--border-color); } toc.nav-pills .nav-link { color: var(--text-secondary); } toc.nav-pills .nav-link.active, toc.nav-pills .show > .nav-link { color: var(--primary-text); background-color: var(--primary); } toc .nav .nav-link { padding-left: 2rem; font-size: 0.9rem; } toc .nav .nav .nav-link { padding-left: 3rem; } // Dark mode form adjustments [data-theme=\"dark\"] .form-control:focus, [data-theme=\"dark\"] .form-select:focus, [data-theme=\"dark\"] input:focus, [data-theme=\"dark\"] textarea:focus, body.dark-mode .form-control:focus, body.dark-mode .form-select:focus, body.dark-mode input:focus, body.dark-mode textarea:focus { box-shadow: 0 0 0 3px rgba(220, 38, 38, 0.2) !important; } // Enhanced table styling table { background: var(--bg-primary) !important; color: var(--text-primary) !important; border-collapse: collapse; width: 100%; } thead th { background: var(--bg-secondary) !important; color: var(--text-primary) !important; border-bottom: 2px solid var(--border-dark) !important; font-weight: 600; padding: 0.75rem; text-align: left; } tbody tr { border-bottom: 1px solid var(--border-color) !important; &:hover { background: var(--bg-muted) !important; } &:nth-child(even) { background: var(--bg-secondary) !important; } &:nth-child(even):hover { background: var(--bg-muted) !important; } } tbody td { color: var(--text-primary) !important; padding: 0.75rem; vertical-align: top; } // Enhanced navbar mobile responsiveness @media (max-width: 991.98px) { .navbar-collapse { background: var(--heidelberg-red) !important; border-radius: var(--radius-lg); margin-top: 0.5rem; padding: 1rem; box-shadow: var(--shadow-md); } [data-theme=\"dark\"] .navbar-collapse, body.dark-mode .navbar-collapse { background: var(--heidelberg-red-darker) !important; } .navbar-nav { gap: 0.25rem; } .navbar-nav .nav-link { padding: 0.75rem 1rem !important; border-radius: var(--radius-md); margin: 0.125rem 0; min-height: 44px; // Accessibility } } // Utility classes .text-center { text-align: center; } .text-left { text-align: left; } .text-right { text-align: right; } .text-justify { text-align: justify; } .fw-normal { font-weight: 400; } .fw-medium { font-weight: 500; } .fw-semibold { font-weight: 600; } .fw-bold { font-weight: 700; } .d-none { display: none; } .d-block { display: block; } .d-inline { display: inline; } .d-inline-block { display: inline-block; } .d-flex { display: flex; } .flex-column { flex-direction: column; } .flex-row { flex-direction: row; } .justify-content-center { justify-content: center; } .justify-content-between { justify-content: space-between; } .align-items-center { align-items: center; } .gap-1 { gap: var(--space-xs); } .gap-2 { gap: var(--space-sm); } .gap-3 { gap: var(--space-md); } .gap-4 { gap: var(--space-lg); } .p-0 { padding: 0; } .p-1 { padding: var(--space-xs); } .p-2 { padding: var(--space-sm); } .p-3 { padding: var(--space-md); } .p-4 { padding: var(--space-lg); } .m-0 { margin: 0; } .m-1 { margin: var(--space-xs); } .m-2 { margin: var(--space-sm); } .m-3 { margin: var(--space-md); } .m-4 { margin: var(--space-lg); } .mt-0 { margin-top: 0; } .mt-1 { margin-top: var(--space-xs); } .mt-2 { margin-top: var(--space-sm); } .mt-3 { margin-top: var(--space-md); } .mt-4 { margin-top: var(--space-lg); } .mb-0 { margin-bottom: 0; } .mb-1 { margin-bottom: var(--space-xs); } .mb-2 { margin-bottom: var(--space-sm); } .mb-3 { margin-bottom: var(--space-md); } .mb-4 { margin-bottom: var(--space-lg); } .me-1 { margin-right: var(--space-xs); } .me-2 { margin-right: var(--space-sm); } .me-3 { margin-right: var(--space-md); } .ms-auto { margin-left: auto; } .me-auto { margin-right: auto; } // Responsive utilities @media (max-width: 576px) { .d-sm-none { display: none; } .d-sm-block { display: block; } } @media (min-width: 768px) { .d-md-none { display: none; } .d-md-block { display: block; } .d-md-flex { display: flex; } } @media (min-width: 992px) { .d-lg-none { display: none; } .d-lg-block { display: block; } .d-lg-flex { display: flex; } } // Mobile font size adjustments @media (max-width: 768px) { h1 { font-size: var(--text-3xl); } h2 { font-size: var(--text-2xl); } h3 { font-size: var(--text-xl); } h4 { font-size: var(--text-lg); } .btn { padding: 0.75rem 1rem; font-size: var(--text-sm); } .card-body, .card-header, .card-footer { padding: var(--space-md); } } // Accessibility enhancements @media (prefers-reduced-motion: reduce) { { animation-duration: 0.01ms !important; animation-iteration-count: 1 !important; transition-duration: 0.01ms !important; } } // High contrast mode support @media (prefers-contrast: high) { .btn, .form-control, .search-input { border-width: 2px; } .card { border-width: 2px; } } // Print styles @media print { { background: white !important; color: black !important; box-shadow: none !important; } .navbar, .floating-controls, .theme-switcher, .skip-link { display: none !important; } a[href]:after { content: \" (\" attr(href) \")\"; font-size: 0.8em; color: 666; } } // Additional search enhancements .search-shortcut-triggered { animation: searchShortcutPulse 0.3s ease; } @keyframes searchShortcutPulse { 0% { transform: scale(1); } 50% { transform: scale(1.05); } 100% { transform: scale(1); } } // Enhanced search container states .search-container { &.search-focused { background: rgba(255, 255, 255, 0.18); border-color: var(--primary); box-shadow: 0 0 0 4px rgba(220, 38, 38, 0.2), 0 15px 35px -5px rgba(0, 0, 0, 0.15); } &.search-active { background: rgba(255, 255, 255, 0.2); border-color: rgba(255, 255, 255, 0.4); } } // Improved search input states .search-input { &:focus { background: rgba(255, 255, 255, 0.08); box-shadow: inset 0 2px 4px rgba(0, 0, 0, 0.1); } &:hover:not(:focus) { background: rgba(255, 255, 255, 0.03); } } // Enhanced search toggle button states .search-toggle-btn { &:focus { outline: none; box-shadow: 0 0 0 3px rgba(255, 255, 255, 0.3); } &:active { transform: translateY(1px) scale(0.95); } &.search-active { background: rgba(255, 255, 255, 0.2); border-color: rgba(255, 255, 255, 0.4); i { transform: scale(1.1); color: var(--primary); } } } // Enhanced search results with better animations .search-results-container { &.show { animation: searchResultsSlideIn 0.3s cubic-bezier(0.4, 0, 0.2, 1); } // Improved scrollbar styling &::-webkit-scrollbar { width: 6px; } &::-webkit-scrollbar-track { background: var(--bg-secondary); border-radius: 3px; } &::-webkit-scrollbar-thumb { background: var(--border-color); border-radius: 3px; &:hover { background: var(--text-muted); } } } // Enhanced search result items with better interactions .search-result-item { &:hover { .search-result-title { color: var(--primary); } } &.active { background: var(--bg-secondary); border-left: 3px solid var(--primary); .search-result-title { color: var(--primary); } } // Improved loading state &.loading { opacity: 0.6; pointer-events: none; } } // Enhanced search result content .search-result-content { position: relative; &::after { content: ''; position: absolute; bottom: 0; left: 0; right: 0; height: 1px; background: linear-gradient(90deg, transparent, var(--border-color), transparent); opacity: 0; transition: opacity 0.2s ease; } } .search-result-item:hover .search-result-content::after { opacity: 1; } // Enhanced search highlighting .search-result-item mark { position: relative; &::before { content: ''; position: absolute; top: 0; left: 0; right: 0; bottom: 0; background: currentColor; opacity: 0.1; border-radius: 0.25rem; z-index: -1; } } // Enhanced empty state .search-empty-state { position: relative; &::before { content: ''; position: absolute; top: 50%; left: 50%; transform: translate(-50%, -50%); width: 4rem; height: 4rem; background: radial-gradient(circle, var(--border-color) 1px, transparent 1px); background-size: 1rem 1rem; opacity: 0.1; z-index: -1; } i { position: relative; z-index: 1; } } // Enhanced loading states .search-loading-state { position: relative; .search-spinner { position: relative; &::after { content: ''; position: absolute; top: -2px; left: -2px; right: -2px; bottom: -2px; border: 2px solid transparent; border-top: 2px solid var(--primary); border-radius: 50%; animation: spin 1.5s linear infinite reverse; opacity: 0.3; } } } // Enhanced typing indicator .search-typing-indicator { .typing-dots { span { background: var(--primary); box-shadow: 0 0 4px rgba(220, 38, 38, 0.3); } } } // Responsive improvements @media (max-width: 768px) { .search-container { margin: 0.5rem 0; &:hover { transform: none; } &:focus-within { transform: none; } } .search-results-container { max-height: 60vh; } .search-result-item { padding: 0.875rem 1rem; &:hover { transform: translateX(2px); } } } // Accessibility improvements @media (prefers-reduced-motion: reduce) { .search-container, .search-toggle-btn, .search-result-item, .search-results-container { transition: none; animation: none; } .search-spinner, .typing-dots span { animation: none; } } // High contrast mode improvements @media (prefers-contrast: high) { .search-container { border-width: 2px; background: var(--bg-primary); } .search-toggle-btn { border-width: 2px; } .search-result-item { border-bottom-width: 2px; } .search-result-item mark { background: var(--primary); color: var(--white); border: 1px solid var(--primary); } } // Enhanced header control buttons .header-control-btn { display: flex; align-items: center; justify-content: center; width: 44px; height: 44px; border-radius: 0.75rem; transition: all 0.2s cubic-bezier(0.4, 0, 0.2, 1); background: rgba(255, 255, 255, 0.1); border: 1px solid rgba(255, 255, 255, 0.2); color: var(--white); cursor: pointer; position: relative; overflow: hidden; font-size: 0.9rem; font-weight: 500; } .header-control-btn::before { content: ''; position: absolute; top: 0; left: 0; right: 0; bottom: 0; background: linear-gradient(135deg, rgba(255, 255, 255, 0.1), rgba(255, 255, 255, 0.05)); opacity: 0; transition: opacity 0.2s ease; } .header-control-btn:hover { background: rgba(255, 255, 255, 0.15); border-color: rgba(255, 255, 255, 0.3); transform: translateY(-1px) scale(1.02); box-shadow: 0 4px 12px rgba(0, 0, 0, 0.15); } .header-control-btn:hover::before { opacity: 1; } .header-control-btn:active { transform: translateY(0) scale(0.98); } .header-control-btn:focus { outline: none; box-shadow: 0 0 0 3px rgba(255, 255, 255, 0.3); } .header-control-btn i { font-size: 1rem; position: relative; z-index: 1; transition: transform 0.2s ease; } .header-control-btn:hover i { transform: scale(1.1); } // Language switcher specific styles .header-control-btn .flag-icon { width: 1.2rem; height: 1.2rem; margin-right: 0.25rem; position: relative; z-index: 1; } .header-control-btn .language-code { font-size: 0.8rem; font-weight: 600; position: relative; z-index: 1; } // Theme toggle specific styles .header-control-btn theme-toggle { .theme-icon { transition: transform 0.3s ease; } &:hover .theme-icon { transform: rotate(15deg) scale(1.1); } } // Pages CMS Admin button specific styles .header-control-btn pagescms-admin-toggle { .fa-cog { transition: transform 0.3s ease; } &:hover .fa-cog { transform: rotate(90deg) scale(1.1); } &.active { background: rgba(255, 255, 255, 0.2); border-color: var(--primary); .fa-cog { color: var(--primary); } } } // Mobile responsive adjustments for header controls @media (max-width: 768px) { .header-control-btn { width: 40px; height: 40px; font-size: 0.85rem; } .header-control-btn .flag-icon { width: 1.1rem; height: 1.1rem; } .header-control-btn .language-code { font-size: 0.75rem; } } @media (max-width: 576px) { .header-control-btn { width: 38px; height: 38px; } .header-control-btn i { font-size: 0.9rem; } } // Search System Styles // Modern, accessible, and responsive search interface // Search Container Styles .search-container { position: relative; width: 100%; max-width: 600px; margin: 0 auto; transition: all 0.3s cubic-bezier(0.4, 0, 0.2, 1); } .search-container-center { display: flex; justify-content: center; align-items: center; flex: 1; margin: 0 2rem; } // Search Input Styles .search-input-wrapper { position: relative; width: 100%; transition: all 0.3s ease; } .search-input-icon { position: absolute; left: 1rem; top: 50%; transform: translateY(-50%); color: rgba(255, 255, 255, 0.7); font-size: 1.1rem; pointer-events: none; transition: all 0.2s ease; z-index: 2; } .search-input { width: 100%; background: rgba(255, 255, 255, 0.1); border: 2px solid rgba(255, 255, 255, 0.2); border-radius: 1rem; color: var(--white); font-size: 0.95rem; font-weight: 500; padding: 0.875rem 1rem 0.875rem 3rem; transition: all 0.3s cubic-bezier(0.4, 0, 0.2, 1); min-height: 52px; letter-spacing: 0.025em; backdrop-filter: blur(10px); } .search-input::placeholder { color: rgba(255, 255, 255, 0.6); font-weight: 400; transition: color 0.2s ease; } .search-input:focus { outline: none; background: rgba(255, 255, 255, 0.15); border-color: rgba(255, 255, 255, 0.4); box-shadow: 0 0 0 4px rgba(255, 255, 255, 0.1); transform: translateY(-1px); } .search-input:focus::placeholder { color: rgba(255, 255, 255, 0.4); } .search-input:focus + .search-input-icon { color: var(--white); transform: translateY(-50%) scale(1.1); } .search-input.search-loading { background: rgba(255, 255, 255, 0.2); } .search-input.search-loading + .search-input-icon { animation: searchPulse 1.5s ease-in-out infinite; } // Search Results Container .search-results-container { position: absolute; top: calc(100% + 0.5rem); left: 0; right: 0; background: var(--white); border-radius: 1rem; box-shadow: 0 20px 25px -5px rgba(0, 0, 0, 0.1), 0 10px 10px -5px rgba(0, 0, 0, 0.04); border: 1px solid rgba(0, 0, 0, 0.1); max-height: 500px; overflow-y: auto; z-index: 1000; display: none; } // Search Result Items .search-result-item { display: flex; align-items: flex-start; padding: 1rem; border-bottom: 1px solid rgba(0, 0, 0, 0.05); cursor: pointer; transition: all 0.2s ease; } .search-result-item:last-child { border-bottom: none; } .search-result-item:hover { background: rgba(0, 0, 0, 0.02); transform: translateX(4px); } .search-result-item.search-result-selected { background: rgba(59, 130, 246, 0.1); border-left: 3px solid 3B82F6; } .search-result-item:active { transform: scale(0.98); } .search-result-icon { flex-shrink: 0; width: 40px; height: 40px; border-radius: 0.75rem; display: flex; align-items: center; justify-content: center; margin-right: 1rem; font-size: 1.1rem; transition: all 0.2s ease; } .search-result-content { flex: 1; min-width: 0; } .search-result-header { display: flex; align-items: flex-start; justify-content: space-between; margin-bottom: 0.5rem; gap: 0.5rem; } .search-result-title { font-size: 0.95rem; font-weight: 600; color: var(--text-primary); margin: 0; line-height: 1.3; flex: 1; min-width: 0; } .search-result-category { font-size: 0.75rem; font-weight: 500; padding: 0.25rem 0.5rem; border-radius: 0.5rem; background: rgba(0, 0, 0, 0.05); white-space: nowrap; flex-shrink: 0; } .search-result-description { font-size: 0.85rem; color: var(--text-secondary); line-height: 1.4; margin-bottom: 0.5rem; display: -webkit-box; -webkit-line-clamp: 2; -webkit-box-orient: vertical; overflow: hidden; } .search-result-meta { display: flex; align-items: center; gap: 1rem; font-size: 0.75rem; color: var(--text-muted); } .search-result-url { font-family: 'Monaco', 'Menlo', 'Ubuntu Mono', monospace; background: rgba(0, 0, 0, 0.05); padding: 0.125rem 0.375rem; border-radius: 0.25rem; overflow: hidden; text-overflow: ellipsis; white-space: nowrap; max-width: 200px; } .search-result-date { color: var(--text-muted); } // Search Highlight .search-highlight { background: rgba(255, 193, 7, 0.3); color: inherit; padding: 0.125rem 0.25rem; border-radius: 0.25rem; font-weight: 600; } // Empty State .search-empty-state { padding: 2rem; text-align: center; color: var(--text-muted); } .search-empty-icon { font-size: 2rem; margin-bottom: 1rem; opacity: 0.5; } .search-empty-content h4 { margin: 0 0 0.5rem 0; font-size: 1rem; font-weight: 600; } .search-empty-content p { margin: 0 0 0.5rem 0; font-size: 0.9rem; } .search-empty-content small { font-size: 0.8rem; opacity: 0.7; } // Error State .search-error-state { padding: 1.5rem; text-align: center; color: EF4444; } .search-error-state i { font-size: 1.5rem; margin-bottom: 0.5rem; display: block; } .search-error-state p { margin: 0; font-size: 0.9rem; } // Search Overlay (Mobile) .search-overlay { position: fixed; top: 0; left: 0; right: 0; bottom: 0; background: rgba(0, 0, 0, 0.8); backdrop-filter: blur(8px); z-index: 9999; opacity: 0; visibility: hidden; transition: all 0.3s cubic-bezier(0.4, 0, 0.2, 1); } .search-overlay.search-overlay-active { opacity: 1; visibility: visible; } .search-overlay-content { position: absolute; top: 0; left: 0; right: 0; bottom: 0; background: var(--white); display: flex; flex-direction: column; transform: translateY(-100%); transition: transform 0.3s cubic-bezier(0.4, 0, 0.2, 1); } .search-overlay.search-overlay-active .search-overlay-content { transform: translateY(0); } .search-overlay-header { display: flex; align-items: center; justify-content: space-between; padding: 1rem 1.5rem; border-bottom: 1px solid rgba(0, 0, 0, 0.1); background: var(--white); } .search-overlay-header h3 { margin: 0; font-size: 1.25rem; font-weight: 600; color: var(--text-primary); } .search-overlay-close { background: none; border: none; font-size: 1.5rem; color: var(--text-muted); cursor: pointer; padding: 0.5rem; border-radius: 0.5rem; transition: all 0.2s ease; } .search-overlay-close:hover { background: rgba(0, 0, 0, 0.05); color: var(--text-primary); } .search-overlay-input-container { position: relative; padding: 1rem 1.5rem; background: var(--white); border-bottom: 1px solid rgba(0, 0, 0, 0.1); } .search-overlay-input-container i { position: absolute; left: 2rem; top: 50%; transform: translateY(-50%); color: var(--text-muted); font-size: 1.1rem; pointer-events: none; } .search-overlay-input { width: 100%; background: rgba(0, 0, 0, 0.05); border: 2px solid transparent; border-radius: 1rem; padding: 0.875rem 1rem 0.875rem 3rem; font-size: 1rem; transition: all 0.2s ease; } .search-overlay-input:focus { outline: none; background: var(--white); border-color: 3B82F6; box-shadow: 0 0 0 3px rgba(59, 130, 246, 0.1); } .search-overlay-results { flex: 1; overflow-y: auto; padding: 0; } .search-overlay-results .search-result-item { margin: 0; border-radius: 0; } // Focus States .search-focused .search-input { transform: translateY(-2px); box-shadow: 0 8px 25px -5px rgba(0, 0, 0, 0.1), 0 4px 10px -5px rgba(0, 0, 0, 0.04); } // Mobile Responsive @media (max-width: 991.98px) { .search-container-center { display: none; } .search-container { max-width: none; } .search-results-container { position: fixed; top: auto; bottom: 0; left: 0; right: 0; max-height: 60vh; border-radius: 1rem 1rem 0 0; border: none; box-shadow: 0 -10px 25px -5px rgba(0, 0, 0, 0.1); } .search-container.search-active .search-results-container { display: block; } } // Dark Mode Support [data-theme=\"dark\"] .search-results-container, body.dark-mode .search-results-container { background: var(--dark-bg); border-color: rgba(255, 255, 255, 0.1); box-shadow: 0 20px 25px -5px rgba(0, 0, 0, 0.3), 0 10px 10px -5px rgba(0, 0, 0, 0.2); } [data-theme=\"dark\"] .search-results-container .search-result-item, body.dark-mode .search-results-container .search-result-item { border-bottom-color: rgba(255, 255, 255, 0.1); } [data-theme=\"dark\"] .search-results-container .search-result-item:hover, body.dark-mode .search-results-container .search-result-item:hover { background: rgba(255, 255, 255, 0.05); } [data-theme=\"dark\"] .search-results-container .search-result-item.search-result-selected, body.dark-mode .search-results-container .search-result-item.search-result-selected { background: rgba(59, 130, 246, 0.2); } [data-theme=\"dark\"] .search-results-container .search-result-title, body.dark-mode .search-results-container .search-result-title { color: var(--white); } [data-theme=\"dark\"] .search-results-container .search-result-description, body.dark-mode .search-results-container .search-result-description { color: rgba(255, 255, 255, 0.7); } [data-theme=\"dark\"] .search-results-container .search-result-url, body.dark-mode .search-results-container .search-result-url { background: rgba(255, 255, 255, 0.1); } [data-theme=\"dark\"] .search-results-container .search-result-category, body.dark-mode .search-results-container .search-result-category { background: rgba(255, 255, 255, 0.1); } [data-theme=\"dark\"] .search-overlay-content, body.dark-mode .search-overlay-content { background: var(--dark-bg); } [data-theme=\"dark\"] .search-overlay-content .search-overlay-header, body.dark-mode .search-overlay-content .search-overlay-header { background: var(--dark-bg); border-bottom-color: rgba(255, 255, 255, 0.1); } [data-theme=\"dark\"] .search-overlay-content .search-overlay-header h3, body.dark-mode .search-overlay-content .search-overlay-header h3 { color: var(--white); } [data-theme=\"dark\"] .search-overlay-content .search-overlay-input-container, body.dark-mode .search-overlay-content .search-overlay-input-container { background: var(--dark-bg); border-bottom-color: rgba(255, 255, 255, 0.1); } [data-theme=\"dark\"] .search-overlay-content .search-overlay-input, body.dark-mode .search-overlay-content .search-overlay-input { background: rgba(255, 255, 255, 0.1); color: var(--white); } [data-theme=\"dark\"] .search-overlay-content .search-overlay-input:focus, body.dark-mode .search-overlay-content .search-overlay-input:focus { background: var(--dark-bg); } // Animations @keyframes searchResultSlideIn { from { opacity: 0; transform: translateX(-20px); } to { opacity: 1; transform: translateX(0); } } @keyframes searchPulse { 0%, 100% { opacity: 0.7; transform: translateY(-50%) scale(1); } 50% { opacity: 1; transform: translateY(-50%) scale(1.1); } } // Loading Animation .search-loading-indicator { display: flex; align-items: center; justify-content: center; padding: 2rem; color: var(--text-muted); } .search-loading-indicator .spinner { width: 1.5rem; height: 1.5rem; border: 2px solid rgba(0, 0, 0, 0.1); border-top: 2px solid 3B82F6; border-radius: 50%; animation: spin 1s linear infinite; margin-right: 0.75rem; } @keyframes spin { 0% { transform: rotate(0deg); } 100% { transform: rotate(360deg); } } // Accessibility .search-input:focus-visible, .search-overlay-input:focus-visible { outline: 2px solid 3B82F6; outline-offset: 2px; } .search-result-item:focus-visible { outline: 2px solid 3B82F6; outline-offset: -2px; } // High contrast mode @media (prefers-contrast: high) { .search-input { border-width: 3px; } .search-result-item { border-bottom-width: 2px; } .search-highlight { background: FFD700; color: 000; } } // Reduced motion @media (prefers-reduced-motion: reduce) { .search-container, .search-input, .search-results-container, .search-result-item, .search-overlay, .search-overlay-content { transition: none; } .search-result-item { animation: none; } }","url":"/assets/css/main.css","category":"page","description":"","tags":"","date":null,"layout":null},{"id":"teaching-Abelian Varieties","title":"Abelian Varieties","content":"Abelian Varieties Course Description Seminar on abelian varieties, their geometry, and arithmetic properties. Course Information - Type: Seminar - Language: German/English - Credits: Varies by course type - Prerequisites: Basic knowledge in algebra and number theory (varies by course) Course Content This course covers seminar on abelian varieties, their geometry, and arithmetic properties. Learning Objectives Students will gain: - Deep understanding of abelian varieties - Practical skills in mathematical reasoning and proof techniques - Experience with current research topics in the field - Ability to present mathematical concepts clearly Assessment Assessment methods vary by course type: - Vorlesung (Lecture): Written examination - Seminar: Oral presentation and participation - Proseminar: Oral presentation and written report - Hauptseminar: Advanced oral presentation and research component Materials Course materials will be provided during the semester, including: - Lecture notes and handouts - Recommended reading lists - Problem sets and exercises - Additional resources and references Related Courses This course is part of the Arithmetic Geometry research group's teaching program. Related courses include: - Algebraic Number Theory - Galois Representations - Arithmetic Geometry - Modular Forms --- Course information extracted from the original Heidelberg University teaching program Last updated: 2025-08-02   Seminar Abelian Varieties - Course information and materials. Dr. Banwait, Prof. Dr. BÃ¶ckle en Winter term 2021/22 Abelian Varieties abelian-varieties .md","url":"/teaching/abelian-varieties/","category":"teaching","description":"Abelian Varieties - Course information and materials.","tags":"","semester":"Winter term 2021/22","instructor":"Dr. Banwait, Prof. Dr. BÃ¶ckle","course_type":"Seminar"},{"id":"teaching-Adische RÃ¤ume II","title":"Adische RÃ¤ume II","content":"Adische RÃ¤ume II Course Description Advanced lecture on adic spaces and their applications in arithmetic geometry. Course Information - Type: Vorlesung - Language: German/English - Credits: Varies by course type - Prerequisites: Basic knowledge in algebra and number theory (varies by course) Course Content This course covers advanced lecture on adic spaces and their applications in arithmetic geometry. Learning Objectives Students will gain: - Deep understanding of adische rÃ¤ume ii - Practical skills in mathematical reasoning and proof techniques - Experience with current research topics in the field - Ability to present mathematical concepts clearly Assessment Assessment methods vary by course type: - Vorlesung (Lecture): Written examination - Seminar: Oral presentation and participation - Proseminar: Oral presentation and written report - Hauptseminar: Advanced oral presentation and research component Materials Course materials will be provided during the semester, including: - Lecture notes and handouts - Recommended reading lists - Problem sets and exercises - Additional resources and references Related Courses This course is part of the Arithmetic Geometry research group's teaching program. Related courses include: - Algebraic Number Theory - Galois Representations - Arithmetic Geometry - Modular Forms --- Course information extracted from the original Heidelberg University teaching program Last updated: 2025-08-02   Vorlesung Adische RÃ¤ume II - Course information and materials. Dr. Ludwig en Summer term 2020 Adische RÃ¤ume II adischeraeumeii .md","url":"/teaching/adischeraeumeii/","category":"teaching","description":"Adische RÃ¤ume II - Course information and materials.","tags":"","semester":"Summer term 2020","instructor":"Dr. Ludwig","course_type":"Vorlesung"},{"id":"teaching-Affine Algebraic Groups","title":"Affine Algebraic Groups","content":"Affine Algebraic Groups Course Description Seminar on affine algebraic groups, their structure theory, and representation theory. Course Information - Type: Seminar - Language: German/English - Credits: Varies by course type - Prerequisites: Basic knowledge in algebra and number theory (varies by course) Course Content This course covers seminar on affine algebraic groups, their structure theory, and representation theory. Learning Objectives Students will gain: - Deep understanding of affine algebraic groups - Practical skills in mathematical reasoning and proof techniques - Experience with current research topics in the field - Ability to present mathematical concepts clearly Assessment Assessment methods vary by course type: - Vorlesung (Lecture): Written examination - Seminar: Oral presentation and participation - Proseminar: Oral presentation and written report - Hauptseminar: Advanced oral presentation and research component Materials Course materials will be provided during the semester, including: - Lecture notes and handouts - Recommended reading lists - Problem sets and exercises - Additional resources and references Related Courses This course is part of the Arithmetic Geometry research group's teaching program. Related courses include: - Algebraic Number Theory - Galois Representations - Arithmetic Geometry - Modular Forms --- Course information extracted from the original Heidelberg University teaching program Last updated: 2025-08-02   Seminar Affine Algebraic Groups - Course information and materials. Prof. Dr. BÃ¶ckle, C.V. Sriram en Winter term 2022/23 Affine Algebraic Groups affine-algebraic-groups .md","url":"/teaching/affine-algebraic-groups/","category":"teaching","description":"Affine Algebraic Groups - Course information and materials.","tags":"","semester":"Winter term 2022/23","instructor":"Prof. Dr. BÃ¶ckle, C.V. Sriram","course_type":"Seminar"},{"id":"teaching-Algebraische Geometrie 1","title":"Algebraische Geometrie 1","content":"Algebraische Geometrie 1 Course Description Introduction to algebraic geometry. Course Information - Type: Vorlesung - Language: German/English - Credits: Varies by course type - Prerequisites: Basic knowledge in algebra and number theory (varies by course) Course Content This course covers introduction to algebraic geometry. Learning Objectives Students will gain: - Deep understanding of algebraische geometrie 1 - Practical skills in mathematical reasoning and proof techniques - Experience with current research topics in the field - Ability to present mathematical concepts clearly Assessment Assessment methods vary by course type: - Vorlesung (Lecture): Written examination - Seminar: Oral presentation and participation - Proseminar: Oral presentation and written report - Hauptseminar: Advanced oral presentation and research component Materials Course materials will be provided during the semester, including: - Lecture notes and handouts - Recommended reading lists - Problem sets and exercises - Additional resources and references Related Courses This course is part of the Arithmetic Geometry research group's teaching program. Related courses include: - Algebraic Number Theory - Galois Representations - Arithmetic Geometry - Modular Forms --- Course information extracted from the original Heidelberg University teaching program Last updated: 2025-08-02   Vorlesung Algebraische Geometrie 1 - Course information and materials. Prof. Dr. BÃ¶ckle en Winter term 2012/2013 Algebraische Geometrie 1 ag1-ws2012 .md","url":"/teaching/ag1-ws2012/","category":"teaching","description":"Algebraische Geometrie 1 - Course information and materials.","tags":"","semester":"Winter term 2012/2013","instructor":"Prof. Dr. BÃ¶ckle","course_type":"Vorlesung"},{"id":"teaching-Algebra 2","title":"Algebra 2","content":"Algebra 2 Course Description Advanced algebra course covering ring theory and module theory. Course Information - Type: Vorlesung - Language: German/English - Credits: Varies by course type - Prerequisites: Basic knowledge in algebra and number theory (varies by course) Course Content This course covers advanced algebra course covering ring theory and module theory. Learning Objectives Students will gain: - Deep understanding of algebra 2 - Practical skills in mathematical reasoning and proof techniques - Experience with current research topics in the field - Ability to present mathematical concepts clearly Assessment Assessment methods vary by course type: - Vorlesung (Lecture): Written examination - Seminar: Oral presentation and participation - Proseminar: Oral presentation and written report - Hauptseminar: Advanced oral presentation and research component Materials Course materials will be provided during the semester, including: - Lecture notes and handouts - Recommended reading lists - Problem sets and exercises - Additional resources and references Related Courses This course is part of the Arithmetic Geometry research group's teaching program. Related courses include: - Algebraic Number Theory - Galois Representations - Arithmetic Geometry - Modular Forms --- Course information extracted from the original Heidelberg University teaching program Last updated: 2025-08-02   Vorlesung Algebra 2 - Course information and materials. Dr. Malte Witte, K. Fischer en Summer term 2017 Algebra 2 algebra-2 .md","url":"/teaching/algebra-2/","category":"teaching","description":"Algebra 2 - Course information and materials.","tags":"","semester":"Summer term 2017","instructor":"Dr. Malte Witte, K. Fischer","course_type":"Vorlesung"},{"id":"teaching-Algebraische Zahlentheorie 1","title":"Algebraische Zahlentheorie 1","content":"Algebraische Zahlentheorie 1 Course Description Introduction to algebraic number theory. Course Information - Type: Vorlesung - Language: German/English - Credits: Varies by course type - Prerequisites: Basic knowledge in algebra and number theory (varies by course) Course Content This course covers introduction to algebraic number theory. Learning Objectives Students will gain: - Deep understanding of algebraische zahlentheorie 1 - Practical skills in mathematical reasoning and proof techniques - Experience with current research topics in the field - Ability to present mathematical concepts clearly Assessment Assessment methods vary by course type: - Vorlesung (Lecture): Written examination - Seminar: Oral presentation and participation - Proseminar: Oral presentation and written report - Hauptseminar: Advanced oral presentation and research component Materials Course materials will be provided during the semester, including: - Lecture notes and handouts - Recommended reading lists - Problem sets and exercises - Additional resources and references Related Courses This course is part of the Arithmetic Geometry research group's teaching program. Related courses include: - Algebraic Number Theory - Galois Representations - Arithmetic Geometry - Modular Forms --- Course information extracted from the original Heidelberg University teaching program Last updated: 2025-08-02   Vorlesung Algebraische Zahlentheorie 1 - Course information and materials. Prof. Dr. BÃ¶ckle, Dr. Guiraud en Winter term 2017/18 Algebraische Zahlentheorie 1 algebraische-zahlentheorie-1 .md","url":"/teaching/algebraische-zahlentheorie-1/","category":"teaching","description":"Algebraische Zahlentheorie 1 - Course information and materials.","tags":"","semester":"Winter term 2017/18","instructor":"Prof. Dr. BÃ¶ckle, Dr. Guiraud","course_type":"Vorlesung"},{"id":"teaching-Algebraische Zahlentheorie 2","title":"Algebraische Zahlentheorie 2","content":"Algebraische Zahlentheorie 2 Course Description Advanced lecture on algebraic number theory. Course Information - Type: Vorlesung - Language: German/English - Credits: Varies by course type - Prerequisites: Basic knowledge in algebra and number theory (varies by course) Course Content This course covers advanced lecture on algebraic number theory. Learning Objectives Students will gain: - Deep understanding of algebraische zahlentheorie 2 - Practical skills in mathematical reasoning and proof techniques - Experience with current research topics in the field - Ability to present mathematical concepts clearly Assessment Assessment methods vary by course type: - Vorlesung (Lecture): Written examination - Seminar: Oral presentation and participation - Proseminar: Oral presentation and written report - Hauptseminar: Advanced oral presentation and research component Materials Course materials will be provided during the semester, including: - Lecture notes and handouts - Recommended reading lists - Problem sets and exercises - Additional resources and references Related Courses This course is part of the Arithmetic Geometry research group's teaching program. Related courses include: - Algebraic Number Theory - Galois Representations - Arithmetic Geometry - Modular Forms --- Course information extracted from the original Heidelberg University teaching program Last updated: 2025-08-02   Vorlesung Algebraische Zahlentheorie 2 - Course information and materials. Prof. Dr. BÃ¶ckle, Dr. Conti en Summer term 2018 Algebraische Zahlentheorie 2 algebraische-zahlentheorie-2 .md","url":"/teaching/algebraische-zahlentheorie-2/","category":"teaching","description":"Algebraische Zahlentheorie 2 - Course information and materials.","tags":"","semester":"Summer term 2018","instructor":"Prof. Dr. BÃ¶ckle, Dr. Conti","course_type":"Vorlesung"},{"id":"teaching-Analytic number theory","title":"Analytic number theory","content":"Analytic number theory Course Description Exercise sessions for analytic number theory. Course Information - Type: Exercise sessions - Language: German/English - Credits: Varies by course type - Prerequisites: Basic knowledge in algebra and number theory (varies by course) Course Content This course covers exercise sessions for analytic number theory. Learning Objectives Students will gain: - Deep understanding of analytic number theory - Practical skills in mathematical reasoning and proof techniques - Experience with current research topics in the field - Ability to present mathematical concepts clearly Assessment Assessment methods vary by course type: - Vorlesung (Lecture): Written examination - Seminar: Oral presentation and participation - Proseminar: Oral presentation and written report - Hauptseminar: Advanced oral presentation and research component Materials Course materials will be provided during the semester, including: - Lecture notes and handouts - Recommended reading lists - Problem sets and exercises - Additional resources and references Related Courses This course is part of the Arithmetic Geometry research group's teaching program. Related courses include: - Algebraic Number Theory - Galois Representations - Arithmetic Geometry - Modular Forms --- Course information extracted from the original Heidelberg University teaching program Last updated: 2025-08-02   Exercise sessions Analytic number theory - Course information and materials. Qiu en Winter term 2012/2013 Analytic number theory az1-ws2012 .md","url":"/teaching/az1-ws2012/","category":"teaching","description":"Analytic number theory - Course information and materials.","tags":"","semester":"Winter term 2012/2013","instructor":"Qiu","course_type":"Exercise sessions"},{"id":"teaching-Darstellungstheorie","title":"Darstellungstheorie","content":"Darstellungstheorie Course Description Seminar on representation theory and its applications. Course Information - Type: Seminar - Language: German/English - Credits: Varies by course type - Prerequisites: Basic knowledge in algebra and number theory (varies by course) Course Content This course covers seminar on representation theory and its applications. Learning Objectives Students will gain: - Deep understanding of darstellungstheorie - Practical skills in mathematical reasoning and proof techniques - Experience with current research topics in the field - Ability to present mathematical concepts clearly Assessment Assessment methods vary by course type: - Vorlesung (Lecture): Written examination - Seminar: Oral presentation and participation - Proseminar: Oral presentation and written report - Hauptseminar: Advanced oral presentation and research component Materials Course materials will be provided during the semester, including: - Lecture notes and handouts - Recommended reading lists - Problem sets and exercises - Additional resources and references Related Courses This course is part of the Arithmetic Geometry research group's teaching program. Related courses include: - Algebraic Number Theory - Galois Representations - Arithmetic Geometry - Modular Forms --- Course information extracted from the original Heidelberg University teaching program Last updated: 2025-08-02   Seminar Darstellungstheorie - Course information and materials. Prof. Dr. BÃ¶ckle, Qiu en Summer term 2015 Darstellungstheorie dar-ss2015 .md","url":"/teaching/dar-ss2015/","category":"teaching","description":"Darstellungstheorie - Course information and materials.","tags":"","semester":"Summer term 2015","instructor":"Prof. Dr. BÃ¶ckle, Qiu","course_type":"Seminar"},{"id":"teaching-Derivierte Kategorien und Algebraische Geometrie","title":"Derivierte Kategorien und Algebraische Geometrie","content":"Derivierte Kategorien und Algebraische Geometrie Course Description Seminar on derived categories and their applications in algebraic geometry. Course Information - Type: Seminar - Language: German/English - Credits: Varies by course type - Prerequisites: Basic knowledge in algebra and number theory (varies by course) Course Content This course covers seminar on derived categories and their applications in algebraic geometry. Learning Objectives Students will gain: - Deep understanding of derivierte kategorien und algebraische geometrie - Practical skills in mathematical reasoning and proof techniques - Experience with current research topics in the field - Ability to present mathematical concepts clearly Assessment Assessment methods vary by course type: - Vorlesung (Lecture): Written examination - Seminar: Oral presentation and participation - Proseminar: Oral presentation and written report - Hauptseminar: Advanced oral presentation and research component Materials Course materials will be provided during the semester, including: - Lecture notes and handouts - Recommended reading lists - Problem sets and exercises - Additional resources and references Related Courses This course is part of the Arithmetic Geometry research group's teaching program. Related courses include: - Algebraic Number Theory - Galois Representations - Arithmetic Geometry - Modular Forms --- Course information extracted from the original Heidelberg University teaching program Last updated: 2025-08-02   Seminar Derivierte Kategorien und Algebraische Geometrie - Course information and materials. Prof. Dr. BÃ¶ckle, Dr. Ludwig en Summer term 2021 Derivierte Kategorien und Algebraische Geometrie derivierte-kategorien .md","url":"/teaching/derivierte-kategorien/","category":"teaching","description":"Derivierte Kategorien und Algebraische Geometrie - Course information and materials.","tags":"","semester":"Summer term 2021","instructor":"Prof. Dr. BÃ¶ckle, Dr. Ludwig","course_type":"Seminar"},{"id":"teaching-KlassenkÃ¶rpertheorie Ã¼ber FunktionenkÃ¶rpern und Drinfeld Moduln","title":"KlassenkÃ¶rpertheorie Ã¼ber FunktionenkÃ¶rpern und Drinfeld Moduln","content":"KlassenkÃ¶rpertheorie Ã¼ber FunktionenkÃ¶rpern und Drinfeld Moduln Course Description Seminar on class field theory over function fields and Drinfeld modules. Course Information - Type: Seminar - Language: German/English - Credits: Varies by course type - Prerequisites: Basic knowledge in algebra and number theory (varies by course) Course Content This course covers seminar on class field theory over function fields and drinfeld modules. Learning Objectives Students will gain: - Deep understanding of klassenkÃ¶rpertheorie Ã¼ber funktionenkÃ¶rpern und drinfeld moduln - Practical skills in mathematical reasoning and proof techniques - Experience with current research topics in the field - Ability to present mathematical concepts clearly Assessment Assessment methods vary by course type: - Vorlesung (Lecture): Written examination - Seminar: Oral presentation and participation - Proseminar: Oral presentation and written report - Hauptseminar: Advanced oral presentation and research component Materials Course materials will be provided during the semester, including: - Lecture notes and handouts - Recommended reading lists - Problem sets and exercises - Additional resources and references Related Courses This course is part of the Arithmetic Geometry research group's teaching program. Related courses include: - Algebraic Number Theory - Galois Representations - Arithmetic Geometry - Modular Forms --- Course information extracted from the original Heidelberg University teaching program Last updated: 2025-08-02   Seminar KlassenkÃ¶rpertheorie Ã¼ber FunktionenkÃ¶rpern und Drinfeld Moduln - Course information and materials. Prof. Dr. BÃ¶ckle, Qiu en Winter term 2014/15 KlassenkÃ¶rpertheorie Ã¼ber FunktionenkÃ¶rpern und Drinfeld Moduln dm-ws2014 .md","url":"/teaching/dm-ws2014/","category":"teaching","description":"KlassenkÃ¶rpertheorie Ã¼ber FunktionenkÃ¶rpern und Drinfeld Moduln - Course information and materials.","tags":"","semester":"Winter term 2014/15","instructor":"Prof. Dr. BÃ¶ckle, Qiu","course_type":"Seminar"},{"id":"teaching-Teaching Documents","title":"Teaching Documents","content":"Teaching Documents This page contains course materials, syllabi, and other teaching documents. Course Materials Note: Course materials will be added here as they become available. Syllabi Note: Course syllabi will be posted here. Additional Resources Note: Additional teaching resources will be added here. --- For current teaching activities, please see the main Teaching page.   Teaching Documents index .md","url":"/teaching/documents/","category":"teaching","description":"","tags":"","semester":"","instructor":"","course_type":""},{"id":"teaching-Funktionentheorie 2","title":"Funktionentheorie 2","content":"Funktionentheorie 2 Course Description Advanced lecture on complex function theory. Course Information - Type: Vorlesung - Language: German/English - Credits: Varies by course type - Prerequisites: Basic knowledge in algebra and number theory (varies by course) Course Content This course covers advanced lecture on complex function theory. Learning Objectives Students will gain: - Deep understanding of funktionentheorie 2 - Practical skills in mathematical reasoning and proof techniques - Experience with current research topics in the field - Ability to present mathematical concepts clearly Assessment Assessment methods vary by course type: - Vorlesung (Lecture): Written examination - Seminar: Oral presentation and participation - Proseminar: Oral presentation and written report - Hauptseminar: Advanced oral presentation and research component Materials Course materials will be provided during the semester, including: - Lecture notes and handouts - Recommended reading lists - Problem sets and exercises - Additional resources and references Related Courses This course is part of the Arithmetic Geometry research group's teaching program. Related courses include: - Algebraic Number Theory - Galois Representations - Arithmetic Geometry - Modular Forms --- Course information extracted from the original Heidelberg University teaching program Last updated: 2025-08-02   Vorlesung Funktionentheorie 2 - Course information and materials. Dr. Maurischat, Quast en Winter term 2018/19 Funktionentheorie 2 funktionentheorie-2 .md","url":"/teaching/funktionentheorie-2/","category":"teaching","description":"Funktionentheorie 2 - Course information and materials.","tags":"","semester":"Winter term 2018/19","instructor":"Dr. Maurischat, Quast","course_type":"Vorlesung"},{"id":"teaching-Galois representations and their deformations","title":"Galois representations and their deformations","content":"Galois representations and their deformations Course Description Lecture on Galois representations and deformation theory. Course Information - Type: Vorlesung - Language: German/English - Credits: Varies by course type - Prerequisites: Basic knowledge in algebra and number theory (varies by course) Course Content This course covers lecture on galois representations and deformation theory. Learning Objectives Students will gain: - Deep understanding of galois representations and their deformations - Practical skills in mathematical reasoning and proof techniques - Experience with current research topics in the field - Ability to present mathematical concepts clearly Assessment Assessment methods vary by course type: - Vorlesung (Lecture): Written examination - Seminar: Oral presentation and participation - Proseminar: Oral presentation and written report - Hauptseminar: Advanced oral presentation and research component Materials Course materials will be provided during the semester, including: - Lecture notes and handouts - Recommended reading lists - Problem sets and exercises - Additional resources and references Related Courses This course is part of the Arithmetic Geometry research group's teaching program. Related courses include: - Algebraic Number Theory - Galois Representations - Arithmetic Geometry - Modular Forms --- Course information extracted from the original Heidelberg University teaching program Last updated: 2025-08-02   Vorlesung Galois representations and their deformations - Course information and materials. Dr. Conti en Summer term 2018 Galois representations and their deformations galois-representations-and-their-deformations .md","url":"/teaching/galois-representations-and-their-deformations/","category":"teaching","description":"Galois representations and their deformations - Course information and materials.","tags":"","semester":"Summer term 2018","instructor":"Dr. Conti","course_type":"Vorlesung"},{"id":"teaching-Galoiskohomologie und Galoisdarstellungen","title":"Galoiskohomologie und Galoisdarstellungen","content":"Galoiskohomologie und Galoisdarstellungen Course Description Lecture on Galois cohomology and Galois representations. Course Information - Type: Vorlesung - Language: German/English - Credits: Varies by course type - Prerequisites: Basic knowledge in algebra and number theory (varies by course) Course Content This course covers lecture on galois cohomology and galois representations. Learning Objectives Students will gain: - Deep understanding of galoiskohomologie und galoisdarstellungen - Practical skills in mathematical reasoning and proof techniques - Experience with current research topics in the field - Ability to present mathematical concepts clearly Assessment Assessment methods vary by course type: - Vorlesung (Lecture): Written examination - Seminar: Oral presentation and participation - Proseminar: Oral presentation and written report - Hauptseminar: Advanced oral presentation and research component Materials Course materials will be provided during the semester, including: - Lecture notes and handouts - Recommended reading lists - Problem sets and exercises - Additional resources and references Related Courses This course is part of the Arithmetic Geometry research group's teaching program. Related courses include: - Algebraic Number Theory - Galois Representations - Arithmetic Geometry - Modular Forms --- Course information extracted from the original Heidelberg University teaching program Last updated: 2025-08-02   Vorlesung Galoiskohomologie und Galoisdarstellungen - Course information and materials. Prof. Dr. BÃ¶ckle en Winter term 2018/19 Galoiskohomologie und Galoisdarstellungen galoiskohomologie .md","url":"/teaching/galoiskohomologie/","category":"teaching","description":"Galoiskohomologie und Galoisdarstellungen - Course information and materials.","tags":"","semester":"Winter term 2018/19","instructor":"Prof. Dr. BÃ¶ckle","course_type":"Vorlesung"},{"id":"teaching-Arithmetik von Zahl- und FunktionenkÃ¶rpern","title":"Arithmetik von Zahl- und FunktionenkÃ¶rpern","content":"Arithmetik von Zahl- und FunktionenkÃ¶rpern Course Description Main seminar on arithmetic of number fields and function fields. Course Information - Type: Hauptseminar - Language: German/English - Credits: Varies by course type - Prerequisites: Basic knowledge in algebra and number theory (varies by course) Course Content This course covers main seminar on arithmetic of number fields and function fields. Learning Objectives Students will gain: - Deep understanding of arithmetik von zahl- und funktionenkÃ¶rpern - Practical skills in mathematical reasoning and proof techniques - Experience with current research topics in the field - Ability to present mathematical concepts clearly Assessment Assessment methods vary by course type: - Vorlesung (Lecture): Written examination - Seminar: Oral presentation and participation - Proseminar: Oral presentation and written report - Hauptseminar: Advanced oral presentation and research component Materials Course materials will be provided during the semester, including: - Lecture notes and handouts - Recommended reading lists - Problem sets and exercises - Additional resources and references Related Courses This course is part of the Arithmetic Geometry research group's teaching program. Related courses include: - Algebraic Number Theory - Galois Representations - Arithmetic Geometry - Modular Forms --- Course information extracted from the original Heidelberg University teaching program Last updated: 2025-08-02   Hauptseminar Arithmetik von Zahl- und FunktionenkÃ¶rpern - Course information and materials. Prof. Dr. BÃ¶ckle, Dr. Maurischat, Gazda en Summer term 2018 Arithmetik von Zahl- und FunktionenkÃ¶rpern hauptseminar-ss2018 .md","url":"/teaching/hauptseminar-ss2018/","category":"teaching","description":"Arithmetik von Zahl- und FunktionenkÃ¶rpern - Course information and materials.","tags":"","semester":"Summer term 2018","instructor":"Prof. Dr. BÃ¶ckle, Dr. Maurischat, Gazda","course_type":"Hauptseminar"},{"id":"teaching-Heidelberg University Arithmetic Geometry Teaching Archive","title":"Heidelberg University Arithmetic Geometry Teaching Archive","content":"Heidelberg University Arithmetic Geometry Teaching Archive This page contains an archive of teaching materials from the Arithmetic Geometry group at Heidelberg University, including course announcements, seminar programs, and lecture materials. Summer Term 2025 - Seminar on \"Homological Algebra\" (Prof. Dr. BÃ¶ckle, Dr. Ferraro) - Course Details Winter Term 2024/25 - Seminar on \"Commutative Algebra\" (Prof. Dr. BÃ¶ckle, Dr. Conti) - Course Announcement PDF - Course Details - Vorlesung \"Modularity and Galois Representations\" (Prof. Dr. BÃ¶ckle, Shavali) - Course Details - Hauptseminar Arithmetik von Zahl- und FunktionenkÃ¶rpern: \"Congruence Modules and the WilesâLenstraâDiamond Numerical Criterion in Higher Codimension\" (Prof. Dr. BÃ¶ckle, Dr. Andrea Conti) - Seminar Program PDF - Course Details Summer Term 2024 - Seminar on \"Representation theory of finite groups\" (Prof. Dr. BÃ¶ckle, Chilla, Dr. GezmiÅ) - Course Details - Hauptseminar Arithmetik von Zahl- und FunktionenkÃ¶rpern: \"Shtukas for reductive groups and global Langlands correspondence after Vincent Lafforgue\" (Prof. Dr. BÃ¶ckle, Dr. GezmiÅ, Shavali, C.V. Sriram) - Seminar Program PDF - Vorlesung \"Algebra 2\" (Prof. Dr. BÃ¶ckle, Shavali) - Course Website Winter Term 2023/24 - Proseminar on \"Quadratic forms\" (Prof. Dr. BÃ¶ckle, C.V. Sriram) - Course Details - Vorlesung \"Algebra 1\" (Prof. Dr. BÃ¶ckle, Shavali) - Course Website - Hauptseminar Arithmetik von Zahl- und FunktionenkÃ¶rpern: \"Rigid meromorphic cocycles\" (Prof. Dr. BÃ¶ckle, Dr. GezmiÅ, Dr. Ludwig) - Seminar Program PDF Summer Term 2023 - Vorlesung \"Lineare Algebra 2\" (Prof. Dr. BÃ¶ckle, Dr. Ludwig) - Course Website - Proseminar \"p-adic numbers\" (Dr. BÃ¶ckle, C. V. Sriram) - Course Details - Hauptseminar Arithmetik von Zahl- und FunktionenkÃ¶rpern: \"Vectorial Drinfeld modular forms over Tate algebras\" (Prof. Dr. BÃ¶ckle, Dr. GezmiÅ) - Seminar Program PDF Winter Term 2022/23 - Vorlesung \"Lineare Algebra 1\" (Prof. Dr. BÃ¶ckle, Dr. Ludwig) - Course Website - Seminar on \"Affine Algebraic Groups\" (Prof. Dr. BÃ¶ckle, C.V. Sriram) - Course Details Summer Term 2022 - Proseminar \"Prime numbers and Cryptography\" (Dr. Banwait, C. V. Sriram) - Course Details Winter Term 2021/22 - Seminar \"Abelian Varieties\" (Dr. Banwait, Prof. Dr. BÃ¶ckle) - Course Details - Vorlesung \"Ãtale Kohomologie\" (Prof. Dr. BÃ¶ckle, Chilla, Quast, Sriram) - Vorlesung \"Computational Number Theory\" (Dr. Banwait) - Course Program PDF - Hauptseminar Arithmetik von Zahl- und FunktionenkÃ¶rpern: \"Plectic Stark-Heegner points\" (Prof. Dr. BÃ¶ckle, Dr. GrÃ¤f) Summer Term 2021 - Seminar \"Derivierte Kategorien und Algebraische Geometrie\" (Prof. Dr. BÃ¶ckle, Dr. Ludwig) - Course Details - Vorlesung \"Algebraische Geometrie 2\" (Prof. Dr. BÃ¶ckle, Chilla, Quast) - Course Website - Hauptseminar Arithmetik von Zahl- und FunktionenkÃ¶rpern: \"Higher Hida Theory\" (Dr. GrÃ¤f, Dr. Ludwig) Winter Term 2020/21 - Seminar \"Elliptische Kurven\" (Prof. Dr. BÃ¶ckle, Dr. Ludwig) - Course Details - Vorlesung \"Algebraische Geometrie 1\" (Prof. Dr. BÃ¶ckle, Chilla, Quast) - Course Website Summer Term 2020 - Vorlesung \"Algebra 2\" (Prof. Dr. BÃ¶ckle, Quast) - Course Details - Vorlesung \"Adische RÃ¤ume II\" (Dr. Ludwig) - Course Details Winter Term 2019/20 - Vorlesung \"Algebra 1\" (Prof. Dr. BÃ¶ckle, Dr. Ludwig) - Seminar \"Affine algebraische Gruppen\" (Prof. Dr. BÃ¶ckle, Quast) - Course Details - Hauptseminar Arithmetik von Zahl- und FunktionenkÃ¶rpern (Prof. Dr. BÃ¶ckle) - Seminar Program PDF Summer Term 2019 - Proseminar \"Bilinearformen und klassische Gruppen\" (Prof. Dr. BÃ¶ckle, Quast) - Course Details - Vorlesung \"Kompatible Systeme von Galoisdarstellungen\" (Prof. Dr. BÃ¶ckle, Dr. Conti) - Vorlesung \"p-divisible Gruppen\" (Dr. Ludwig) - Course Details - Hauptseminar Arithmetik von Zahl- und FunktionenkÃ¶rpern (Prof. Dr. BÃ¶ckle, Dr. Ludwig) - Seminar Program PDF Winter Term 2018/19 - Seminar \"Darstellungstheorie von GL 2\" (Prof. Dr. BÃ¶ckle, Dr. Ludwig) - Seminar Program PDF - Seminar \"Algorithmische Algebra\" (Dr. Maurischat) - Vorlesung \"Galoiskohomologie und Galoisdarstellungen\" (Prof. Dr. BÃ¶ckle) - Vorlesung \"Funktionentheorie 2\" (Dr. Maurischat, Quast) - Hauptseminar Arithmetik von Zahl- und FunktionenkÃ¶rpern (Prof. Dr. BÃ¶ckle, Dr. Ludwig) - Seminar Program PDF Summer Term 2018 - Seminar \"Lokale KlassenkÃ¶rpertheorie nach Lubin-Tate\" (Prof. Dr. BÃ¶ckle, Fischer) - Vorlesung \"Algebraische Zahlentheorie 2\" (Prof. Dr. BÃ¶ckle, Dr. Conti) - Vorlesung \"Galois representations and their deformations\" (Dr. Conti) - Hauptseminar Arithmetik von Zahl- und FunktionenkÃ¶rpern (Prof. Dr. BÃ¶ckle, Dr. Maurischat, Gazda) Winter Term 2017/18 - Vorlesung \"Algebraische Zahlentheorie 1\" (Prof. Dr. BÃ¶ckle, Dr. Guiraud) - Seminar \"Gruppenkohomologie\" (Prof. Dr. BÃ¶ckle, Fischer) - Hauptseminar Arithmetik von Zahl- und FunktionenkÃ¶rpern Summer Term 2017 - Vorlesung \"Algebra 2\" (Dr. Malte Witte, K. Fischer) Winter Term 2016/17 - Proseminar \"Primzahlen und Faktorisierung fÃ¼r die Kryptographie\" (Prof. Dr. BÃ¶ckle, Fischer) - Hauptseminar Arithmetik von Zahl- und FunktionenkÃ¶rpern: \"Surveys on some conjectures\" Summer Term 2016 - Vorlesung \"Lineare Algebra 2\" (Prof. Dr. BÃ¶ckle) - Proseminar \"p-adische Analysis\" (Prof. Dr. BÃ¶ckle, GrÃ¤f) - Hauptseminar Arithmetik von Zahl- und FunktionenkÃ¶rpern: \"p-adic Uniformization\" (Prof. Dr. BÃ¶ckle, Dr. Guiraud, Fischer, GrÃ¤f) Winter Term 2015/16 - Vorlesung \"Lineare Algebra 1\" (Prof. Dr. BÃ¶ckle) - Seminar \"Modularity and Patching\" (Prof. Dr. BÃ¶ckle, Fischer, GrÃ¤f) - Seminar Announcement PDF - Hauptseminar Arithmetik von Zahl- und FunktionenkÃ¶rpern: \"Hodge-Pink structures\" (Prof. Dr. BÃ¶ckle, Dr. Perkins, Dr. Juan Cervino) Summer Term 2015 - Vorlesung \"Bruhat-Tits GebÃ¤ude\" (Prof. Dr. BÃ¶ckle) - Course Description PDF - Seminar \"Darstellungstheorie\" (Prof. Dr. BÃ¶ckle, Qiu) - Vorlesung \"Darstellungen und Invarianten 2\" (Dr. CerviÃ±o) - Course Description PDF - Hauptseminar Arithmetik von Zahl- und FunktionenkÃ¶rpern: \"Lenny TaelmanÂ´s body of work on Drinfeld modules\" (Prof. Dr. BÃ¶ckle, Dr. Perkins, Dr. Hubschmid) - Seminar Program PDF Winter Term 2014/15 - Vorlesung \"Automorphe Formen\" (Prof. Dr. BÃ¶ckle) - Course Description PDF - Seminar \"KlassenkÃ¶rpertheorie Ã¼ber FunktionenkÃ¶rpern und Drinfeld Moduln\" (Prof. Dr. BÃ¶ckle, Qiu) - Vorlesung \"Darstellungen und Invarianten\" (Dr. CerviÃ±o) - Course Description PDF - Hauptseminar Arithmetik von Zahl- und FunktionenkÃ¶rpern: \"Recent results towards the BSD conjecture for elliptic curves over Q\" (Prof. Dr. BÃ¶ckle, Dr. CerviÃ±o, Dr. Hubschmid) - Seminar Program PDF Summer Term 2014 - Seminar \"p-adische Geometrie\" (Prof. Dr. BÃ¶ckle, Juschka, Qiu) - Vorlesung \"Algebraische Gruppen\" (Prof. Dr. BÃ¶ckle) - Spezialvorlesung \"Abelsche VarietÃ¤ten II\" (Prof. Dr. BÃ¶ckle, Dr. Centeleghe) - Hauptseminar \"Arithmetik von Zahl- und FunktionenkÃ¶rpern: Shimura Varieties\" (Prof. Dr. BÃ¶ckle, Dr. CerviÃ±o, Fischer) Winter Term 2013/14 - Ãtale Kohomologie (Prof. Dr. BÃ¶ckle) - Seminar \"Deformationen von (Pseudo-)Darstellungen\" (Prof. Dr. BÃ¶ckle, Juschka) - Abelsche VarietÃ¤ten I (Prof. Dr. BÃ¶ckle, Dr. Tommaso Centeleghe) - Arithmetik von Zahl- und FunktionenkÃ¶rpern: \"Modularity Lifting\" (Prof. Dr. BÃ¶ckle, Dr. CerviÃ±o, Fischer) Summer Term 2013 - Algebraische Geometrie 2 (Prof. Dr. BÃ¶ckle) - Seminar \"Torische VarietÃ¤ten\" (Prof. Dr. BÃ¶ckle) - Seminar \"Trianguline Representations\" (Prof. Dr. BÃ¶ckle) - Group cohomology (Dr. CerviÃ±o) - Exercise sessions for \"Lineare Algebra 2\" (Dr. Maurischat) Winter Term 2012/2013 - Algebraische Geometrie 1 (Prof. Dr. BÃ¶ckle) - Seminar \"Affine algebraische Gruppen\" (Prof. Dr. BÃ¶ckle, Dr. CerviÃ±o) - Seminar Program PDF - Exercise sessions for \"Lineare Algebra 1\" (Dr. Maurischat) - Exercise sessions for \"Analytic number theory\" (Qiu) - Seminar \"Transcendence theory in positive characteristic\" (Prof. Dr. BÃ¶ckle, Dr. Hubschmid) - Seminar Program PDF Summer Term 2012 - Algebra 2 (Dr. CerviÃ±o) - Exercise sessions for \"Computeralgebra\" (Dr. Maurischat) - Seminar \"Automorphic Forms and representations of GL2\" (Dr. CerviÃ±o, Dr. Centeleghe) - Seminar Program PDF Winter Term 2011/12 - Algebra 1 (Prof. Dr. BÃ¶ckle) - Proseminar \"Bilinear forms and classical groups\" (Prof. Dr. BÃ¶ckle, Dr. Maurischat) - Seminar \"Borcherds Products\" (Prof. Dr. BÃ¶ckle, Dr. CerviÃ±o) - Seminar Program PDF - Seminar \"Ikeda-Lift\" (Dr. Bouganis, Dr. CerviÃ±o, Dr. Kasten) - Seminar Program PDF Summer Term 2011 - Linear Algebra 2 (Prof. Dr. BÃ¶ckle) - Quadratic Forms (Dr. CerviÃ±o) - Course Program PDF - Proseminar \"Fuchsian groups\" (Prof. Dr. BÃ¶ckle, Dr. Maurischat) - Seminar \"L-functions after V. Lafforgue\" (Prof. Dr. BÃ¶ckle, Dr. Maurischat) - Exercise sessions for \"Elementary number theory\" (Ralf Butenuth) Winter Term 2010/11 - Linear Algebra 1 (Prof. Dr. BÃ¶ckle) - Algebraic groups and buildings (Prof. Dr. BÃ¶ckle, Dr. CerviÃ±o) - Seminar \"Hecke operators and their algorithmic\" (Prof. Dr. BÃ¶ckle, Dr. Centeleghe) - Exercise sessions for \"Introduction to elementary geometry\" (Ralf Butenuth) --- Archive Information This archive contains teaching materials from the Arithmetic Geometry group at Heidelberg University. All PDFs and documents have been preserved for educational and research purposes. Source: Heidelberg University Arithmetic Geometry Group Last Updated: February 2025 Total Files Downloaded: 57 files (PDFs and documents) Archive Size: 7.5 MB  seminar Heidelberg University Arithmetic Geometry Teaching Archive - Course information and materials. Unknown en Unknown Heidelberg University Arithmetic Geometry Teaching Archive heidelberg-teaching-archive .md","url":"/teaching/heidelberg-teaching-archive/","category":"teaching","description":"Heidelberg University Arithmetic Geometry Teaching Archive - Course information and materials.","tags":"","semester":"Unknown","instructor":"Unknown","course_type":"seminar"},{"id":"teaching-Homological Algebra","title":"Homological Algebra","content":"Homological Algebra Course Description Seminar on Homological Algebra covering fundamental concepts and applications in algebraic topology and algebra. Course Information - Type: Seminar - Language: German/English - Credits: Varies by course type - Prerequisites: Basic knowledge in algebra and number theory (varies by course) Course Content This course covers seminar on homological algebra covering fundamental concepts and applications in algebraic topology and algebra. Learning Objectives Students will gain: - Deep understanding of homological algebra - Practical skills in mathematical reasoning and proof techniques - Experience with current research topics in the field - Ability to present mathematical concepts clearly Assessment Assessment methods vary by course type: - Vorlesung (Lecture): Written examination - Seminar: Oral presentation and participation - Proseminar: Oral presentation and written report - Hauptseminar: Advanced oral presentation and research component Materials Course materials will be provided during the semester, including: - Lecture notes and handouts - Recommended reading lists - Problem sets and exercises - Additional resources and references Related Courses This course is part of the Arithmetic Geometry research group's teaching program. Related courses include: - Algebraic Number Theory - Galois Representations - Arithmetic Geometry - Modular Forms --- Course information extracted from the original Heidelberg University teaching program Last updated: 2025-08-02   Seminar Homological Algebra - Course information and materials. Prof. Dr. BÃ¶ckle, Dr. Ferraro en Summer term 2025 Homological Algebra homological-algebra-seminar .md","url":"/teaching/homological-algebra-seminar/","category":"teaching","description":"Homological Algebra - Course information and materials.","tags":"","semester":"Summer term 2025","instructor":"Prof. Dr. BÃ¶ckle, Dr. Ferraro","course_type":"Seminar"},{"id":"teaching-Teaching","title":"Teaching","content":"Teaching Activities Comprehensive overview of current and past teaching activities at Heidelberg University, including lectures, seminars, and research courses in arithmetic geometry, algebra, and number theory. Filter by Type: All Courses Lectures Seminars Proseminars Hauptseminars Filter by Period: All Time Current & Recent (2023-2025) Recent (2020-2022) Historical (2010-2019) Search Courses: Current Teaching Summer term 2025 Seminar Homological Algebra (Prof. Dr. BÃ¶ckle, Dr. Ferraro) Recent Teaching (2020-2025) Winter term 2024/25 Seminar Commutative Algebra (Prof. Dr. BÃ¶ckle, Dr. Conti) Vorlesung Modularity and Galois Representations (Prof. Dr. BÃ¶ckle, Shavali) Hauptseminar Congruence Modules and the WilesâLenstraâDiamond Numerical Criterion in Higher Codimension (Prof. Dr. BÃ¶ckle, Dr. Andrea Conti) Summer term 2024 Seminar Representation theory of finite groups (Prof. Dr. BÃ¶ckle, Chilla, Dr. GezmiÅ) Hauptseminar Shtukas for reductive groups and global Langlands correspondence after Vincent Lafforgue (Prof. Dr. BÃ¶ckle, Dr. GezmiÅ, Shavali, C.V. Sriram) Vorlesung Algebra 2 (Prof. Dr. BÃ¶ckle, Shavali) Winter term 2023/24 Proseminar Quadratic forms (Prof. Dr. BÃ¶ckle, C.V. Sriram) Vorlesung Algebra 1 (Prof. Dr. BÃ¶ckle, Shavali) Hauptseminar Rigid meromorphic cocycles (Prof. Dr. BÃ¶ckle, Dr. GezmiÅ, Dr. Ludwig) Summer term 2023 Vorlesung Lineare Algebra 2 (Prof. Dr. BÃ¶ckle, Dr. Ludwig) Proseminar p-adic numbers (Dr. BÃ¶ckle, C. V. Sriram) Hauptseminar Vectorial Drinfeld modular forms over Tate algebras (Prof. Dr. BÃ¶ckle, Dr. GezmiÅ) Winter term 2022/23 Vorlesung Lineare Algebra 1 (Prof. Dr. BÃ¶ckle, Dr. Ludwig) Seminar Affine Algebraic Groups (Prof. Dr. BÃ¶ckle, C.V. Sriram) Summer term 2022 Proseminar Prime numbers and Cryptography (Dr. Banwait, C. V. Sriram) Winter term 2021/22 Seminar Abelian Varieties (Dr. Banwait, Prof. Dr. BÃ¶ckle) Vorlesung Ãtale Kohomologie (Prof. Dr. BÃ¶ckle, Chilla, Quast, Sriram) Vorlesung Computational Number Theory (Dr. Banwait) Hauptseminar Plectic Stark-Heegner points (Prof. Dr. BÃ¶ckle, Dr. GrÃ¤f) Summer term 2021 Seminar Derivierte Kategorien und Algebraische Geometrie (Prof. Dr. BÃ¶ckle, Dr. Ludwig) Vorlesung Algebraische Geometrie 2 (Prof. Dr. BÃ¶ckle, Chilla, Quast) Hauptseminar Higher Hida Theory (Dr. GrÃ¤f, Dr. Ludwig) Winter term 2020/21 Seminar Elliptische Kurven (Prof. Dr. BÃ¶ckle, Dr. Ludwig) Vorlesung Algebraische Geometrie 1 (Prof. Dr. BÃ¶ckle, Chilla, Quast) Summer term 2020 Vorlesung Algebra 2 (Prof. Dr. BÃ¶ckle, Quast) Vorlesung Adische RÃ¤ume II (Dr. Ludwig) Historical Teaching (2010-2019) Winter term 2019/20 Vorlesung Algebra 1 (Prof. Dr. BÃ¶ckle, Dr. Ludwig) Seminar Affine algebraische Gruppen (Prof. Dr. BÃ¶ckle, Quast) Hauptseminar Arithmetik von Zahl- und FunktionenkÃ¶rpern (Prof. Dr. BÃ¶ckle) Summer term 2019 Proseminar Bilinearformen und klassische Gruppen (Prof. Dr. BÃ¶ckle, Quast) Vorlesung Kompatible Systeme von Galoisdarstellungen (Prof. Dr. BÃ¶ckle, Dr. Conti) Vorlesung p-divisible Gruppen (Dr. Ludwig) Hauptseminar Arithmetik von Zahl- und FunktionenkÃ¶rpern (Prof. Dr. BÃ¶ckle, Dr. Ludwig) Winter term 2018/19 Seminar Darstellungstheorie von GL 2 (Prof. Dr. BÃ¶ckle, Dr. Ludwig) Seminar Algorithmische Algebra (Dr. Maurischat) Vorlesung Galoiskohomologie und Galoisdarstellungen (Prof. Dr. BÃ¶ckle) Vorlesung Funktionentheorie 2 (Dr. Maurischat, Quast) Hauptseminar Arithmetik von Zahl- und FunktionenkÃ¶rpern (Prof. Dr. BÃ¶ckle, Dr. Ludwig) Summer term 2018 Proseminar Primzahlen und Faktorisierung (Dr. Fischer) Vorlesung Algebra 2 (Dr. Fischer) Seminar Lubin-Tate Theorie (Dr. Fischer) Hauptseminar Arithmetik von Zahl- und FunktionenkÃ¶rpern (Prof. Dr. BÃ¶ckle, Dr. Ludwig) Winter term 2017/18 Proseminar Bilinearformen und klassische Gruppen (Prof. Dr. BÃ¶ckle, Quast) Vorlesung Algebra 1 (Dr. Fischer) Seminar Affine algebraische Gruppen (Prof. Dr. BÃ¶ckle, Quast) Hauptseminar Arithmetik von Zahl- und FunktionenkÃ¶rpern (Prof. Dr. BÃ¶ckle, Dr. Ludwig) Summer term 2017 Proseminar Primzahlen und Faktorisierung (Dr. Fischer) Vorlesung Algebra 2 (Dr. Fischer) Seminar Lubin-Tate Theorie (Dr. Fischer) Hauptseminar Arithmetik von Zahl- und FunktionenkÃ¶rpern (Prof. Dr. BÃ¶ckle, Dr. Ludwig) Winter term 2016/17 Proseminar Bilinearformen und klassische Gruppen (Prof. Dr. BÃ¶ckle, Quast) Vorlesung Algebra 1 (Dr. Fischer) Seminar Affine algebraische Gruppen (Prof. Dr. BÃ¶ckle, Quast) Hauptseminar Arithmetik von Zahl- und FunktionenkÃ¶rpern (Prof. Dr. BÃ¶ckle, Dr. Ludwig) Summer term 2016 Proseminar Primzahlen und Faktorisierung (Dr. Fischer) Vorlesung Algebra 2 (Dr. Fischer) Seminar Lubin-Tate Theorie (Dr. Fischer) Hauptseminar Arithmetik von Zahl- und FunktionenkÃ¶rpern (Prof. Dr. BÃ¶ckle, Dr. Ludwig) Winter term 2015/16 Proseminar Bilinearformen und klassische Gruppen (Prof. Dr. BÃ¶ckle, Quast) Vorlesung Algebra 1 (Dr. Fischer) Seminar Affine algebraische Gruppen (Prof. Dr. BÃ¶ckle, Quast) Hauptseminar Arithmetik von Zahl- und FunktionenkÃ¶rpern (Prof. Dr. BÃ¶ckle, Dr. Ludwig) Summer term 2015 Proseminar Primzahlen und Faktorisierung (Dr. Fischer) Vorlesung Algebra 2 (Dr. Fischer) Seminar Lubin-Tate Theorie (Dr. Fischer) Hauptseminar Arithmetik von Zahl- und FunktionenkÃ¶rpern (Prof. Dr. BÃ¶ckle, Dr. Ludwig) Winter term 2014/15 Proseminar Bilinearformen und klassische Gruppen (Prof. Dr. BÃ¶ckle, Quast) Vorlesung Algebra 1 (Dr. Fischer) Seminar Affine algebraische Gruppen (Prof. Dr. BÃ¶ckle, Quast) Hauptseminar Arithmetik von Zahl- und FunktionenkÃ¶rpern (Prof. Dr. BÃ¶ckle, Dr. Ludwig) Summer term 2014 Proseminar Primzahlen und Faktorisierung (Dr. Fischer) Vorlesung Algebra 2 (Dr. Fischer) Seminar Lubin-Tate Theorie (Dr. Fischer) Hauptseminar Arithmetik von Zahl- und FunktionenkÃ¶rpern (Prof. Dr. BÃ¶ckle, Dr. Ludwig) Winter term 2013/14 Proseminar Bilinearformen und klassische Gruppen (Prof. Dr. BÃ¶ckle, Quast) Vorlesung Algebra 1 (Dr. Fischer) Seminar Affine algebraische Gruppen (Prof. Dr. BÃ¶ckle, Quast) Hauptseminar Arithmetik von Zahl- und FunktionenkÃ¶rpern (Prof. Dr. BÃ¶ckle, Dr. Ludwig) Summer term 2013 Proseminar Primzahlen und Faktorisierung (Dr. Fischer) Vorlesung Algebra 2 (Dr. Fischer) Seminar Lubin-Tate Theorie (Dr. Fischer) Hauptseminar Arithmetik von Zahl- und FunktionenkÃ¶rpern (Prof. Dr. BÃ¶ckle, Dr. Ludwig) Winter term 2012/13 Proseminar Bilinearformen und klassische Gruppen (Prof. Dr. BÃ¶ckle, Quast) Vorlesung Algebra 1 (Dr. Fischer) Seminar Affine algebraische Gruppen (Prof. Dr. BÃ¶ckle, Quast) Hauptseminar Arithmetik von Zahl- und FunktionenkÃ¶rpern (Prof. Dr. BÃ¶ckle, Dr. Ludwig) Summer term 2012 Proseminar Primzahlen und Faktorisierung (Dr. Fischer) Vorlesung Algebra 2 (Dr. Fischer) Seminar Lubin-Tate Theorie (Dr. Fischer) Hauptseminar Arithmetik von Zahl- und FunktionenkÃ¶rpern (Prof. Dr. BÃ¶ckle, Dr. Ludwig) Winter term 2011/12 Proseminar Bilinearformen und klassische Gruppen (Prof. Dr. BÃ¶ckle, Quast) Vorlesung Algebra 1 (Dr. Fischer) Seminar Affine algebraische Gruppen (Prof. Dr. BÃ¶ckle, Quast) Hauptseminar Arithmetik von Zahl- und FunktionenkÃ¶rpern (Prof. Dr. BÃ¶ckle, Dr. Ludwig) Summer term 2011 Proseminar Primzahlen und Faktorisierung (Dr. Fischer) Vorlesung Algebra 2 (Dr. Fischer) Seminar Lubin-Tate Theorie (Dr. Fischer) Hauptseminar Arithmetik von Zahl- und FunktionenkÃ¶rpern (Prof. Dr. BÃ¶ckle, Dr. Ludwig) Winter term 2010/11 Proseminar Bilinearformen und klassische Gruppen (Prof. Dr. BÃ¶ckle, Quast) Vorlesung Algebra 1 (Dr. Fischer) Seminar Affine algebraische Gruppen (Prof. Dr. BÃ¶ckle, Quast) Hauptseminar Arithmetik von Zahl- und FunktionenkÃ¶rpern (Prof. Dr. BÃ¶ckle, Dr. Ludwig) Complete historical record from 2010-2019. Use the filters above to search for specific courses or time periods. Contact Information For course inquiries: boeckle@mathi.uni-heidelberg.de Office hours: By appointment Location: Mathematisches Institut, Heidelberg University Last updated: January 2025 .teaching-page { max-width: 1200px; margin: 0 auto; padding: 0 1rem; } / Header Styles / .teaching-header { background: var(--bg-secondary); border-bottom: 3px solid var(--heidelberg-red); padding: 2rem 0; margin: -2rem -2rem 2rem -2rem; border-radius: 0 0 15px 15px; } .teaching-intro { max-width: 800px; margin: 0 auto; text-align: center; padding: 0 2rem; } .teaching-intro h2 { font-size: 2.5rem; margin-bottom: 1rem; font-weight: 600; color: var(--text-primary); } .teaching-intro p { font-size: 1.1rem; line-height: 1.6; color: var(--text-secondary); } / Filter Controls / .filter-controls { background: f8f9fa; border: 1px solid e9ecef; border-radius: 12px; padding: 1.5rem; margin-bottom: 2rem; display: grid; grid-template-columns: repeat(auto-fit, minmax(200px, 1fr)); gap: 1rem; box-shadow: 0 2px 8px rgba(0,0,0,0.05); } .filter-group { display: flex; flex-direction: column; gap: 0.5rem; } .filter-group label { font-weight: 600; color: 495057; font-size: 0.9rem; } .filter-select, .filter-input { padding: 0.75rem; border: 1px solid ced4da; border-radius: 6px; font-size: 0.9rem; background: white; transition: all 0.2s ease; } .filter-select:focus, .filter-input:focus { outline: none; border-color: 667eea; box-shadow: 0 0 0 3px rgba(102, 126, 234, 0.1); } / Section Styles / .teaching-section { margin-bottom: 3rem; } .section-title { font-size: 1.8rem; font-weight: 600; margin-bottom: 1.5rem; padding: 1rem 0; border-bottom: 3px solid; display: flex; align-items: center; gap: 0.75rem; transition: all 0.3s ease; } .section-title i { font-size: 1.2rem; } .current-title { color: 28a745; border-bottom-color: 28a745; } .recent-title { color: 17a2b8; border-bottom-color: 17a2b8; } .historical-title { color: 6c757d; border-bottom-color: 6c757d; } / Semester Groups / .semester-group { margin-bottom: 2rem; padding: 1.5rem; background: white; border-radius: 12px; border: 1px solid e9ecef; box-shadow: 0 2px 8px rgba(0,0,0,0.05); transition: all 0.3s ease; } .semester-group:hover { box-shadow: 0 4px 16px rgba(0,0,0,0.1); transform: translateY(-2px); } .semester-title { font-size: 1.3rem; font-weight: 600; margin-bottom: 1rem; padding: 0.75rem 0; border-bottom: 2px solid; display: flex; align-items: center; gap: 0.5rem; } .current-semester { color: 28a745; border-bottom-color: 28a745; } .recent-semester { color: 17a2b8; border-bottom-color: 17a2b8; } .historical-semester { color: 6c757d; border-bottom-color: 6c757d; } / Course Lists / .course-list { list-style: none; padding: 0; margin: 0; } .course-item { background: f8f9fa; margin: 0.75rem 0; padding: 1rem 1.5rem; border-radius: 8px; border-left: 4px solid 667eea; transition: all 0.3s ease; display: flex; align-items: center; gap: 1rem; flex-wrap: wrap; animation: fadeInUp 0.6s ease forwards; opacity: 0; transform: translateY(20px); } .course-item:hover { background: e3f2fd; transform: translateX(5px); box-shadow: 0 4px 12px rgba(102, 126, 234, 0.15); } .course-item:nth-child(1) { animation-delay: 0.1s; } .course-item:nth-child(2) { animation-delay: 0.2s; } .course-item:nth-child(3) { animation-delay: 0.3s; } .course-item:nth-child(4) { animation-delay: 0.4s; } .course-item.hidden { display: none; } / Course Badges / .course-badge { display: inline-flex; align-items: center; gap: 0.5rem; padding: 0.4rem 0.8rem; border-radius: 20px; font-size: 0.8rem; font-weight: 600; white-space: nowrap; box-shadow: 0 2px 4px rgba(0,0,0,0.1); cursor: pointer; transition: transform 0.2s ease; } .course-badge:hover { transform: scale(1.05); } .course-badge.seminar { background: linear-gradient(135deg, e8f5e8 0%, c8e6c9 100%); color: 27ae60; border: 1px solid a5d6a7; } .course-badge.vorlesung { background: linear-gradient(135deg, e3f2fd 0%, bbdefb 100%); color: 1976d2; border: 1px solid 90caf9; } .course-badge.proseminar { background: linear-gradient(135deg, fff3e0 0%, ffcc02 100%); color: f57c00; border: 1px solid ffb74d; } .course-badge.hauptseminar { background: linear-gradient(135deg, fce4ec 0%, f8bbd9 100%); color: c2185b; border: 1px solid f48fb1; } / Course Links / .course-link { color: 2980b9; text-decoration: none; font-weight: 500; flex: 1; min-width: 200px; transition: color 0.2s ease; } .course-link:hover { color: 1f5f8b; text-decoration: underline; } .instructors { color: 6c757d; font-size: 0.9rem; font-style: italic; white-space: nowrap; } / Historical Content - Always Visible / .historical-content { / Remove max-height and overflow restrictions / } .historical-note { background: fff3cd; border: 1px solid ffeaa7; border-radius: 8px; padding: 1rem; margin-top: 1rem; color: 856404; } .historical-note p { margin: 0; display: flex; align-items: center; gap: 0.5rem; } / Footer / .teaching-footer { background: f8f9fa; border-top: 3px solid 667eea; margin: 3rem -2rem -2rem -2rem; padding: 2rem; border-radius: 15px 15px 0 0; } .footer-content { max-width: 800px; margin: 0 auto; display: grid; grid-template-columns: 2fr 1fr; gap: 2rem; align-items: start; } .contact-info h3 { color: 2c3e50; margin-bottom: 1rem; font-size: 1.2rem; display: flex; align-items: center; gap: 0.5rem; } .contact-info p { margin: 0.5rem 0; color: 555; } .contact-info a { color: 3498db; text-decoration: none; } .contact-info a:hover { text-decoration: underline; } .last-update { text-align: right; color: 7f8c8d; font-size: 0.9rem; } .last-update p { display: flex; align-items: center; gap: 0.5rem; justify-content: flex-end; } / Responsive Design / @media (max-width: 768px) { .teaching-intro h2 { font-size: 2rem; } .filter-controls { grid-template-columns: 1fr; } .course-item { flex-direction: column; align-items: flex-start; gap: 0.5rem; } .course-badge { align-self: flex-start; } .footer-content { grid-template-columns: 1fr; text-align: center; } .last-update { text-align: center; } .last-update p { justify-content: center; } } @media (max-width: 480px) { .course-badge { font-size: 0.7rem; padding: 0.3rem 0.6rem; } .course-link { min-width: auto; } } / Animation for course items / @keyframes fadeInUp { to { opacity: 1; transform: translateY(0); } } / Hidden class for filtering / .semester-group.hidden { display: none; } document.addEventListener('DOMContentLoaded', function() { // Filtering functionality const courseTypeFilter = document.getElementById('courseTypeFilter'); const timeFilter = document.getElementById('timeFilter'); const searchFilter = document.getElementById('searchFilter'); const courseItems = document.querySelectorAll('.course-item'); const semesterGroups = document.querySelectorAll('.semester-group'); function applyFilters() { const selectedType = courseTypeFilter.value; const selectedPeriod = timeFilter.value; const searchTerm = searchFilter.value.toLowerCase(); courseItems.forEach(item => { const type = item.dataset.type; const period = item.dataset.period; const title = item.querySelector('.course-link').textContent.toLowerCase(); const typeMatch = selectedType === 'all' || type === selectedType; const periodMatch = selectedPeriod === 'all' || period === selectedPeriod; const searchMatch = searchTerm === '' || title.includes(searchTerm); if (typeMatch && periodMatch && searchMatch) { item.classList.remove('hidden'); } else { item.classList.add('hidden'); } }); // Hide empty semester groups semesterGroups.forEach(group => { const visibleItems = group.querySelectorAll('.course-item:not(.hidden)'); if (visibleItems.length === 0) { group.classList.add('hidden'); } else { group.classList.remove('hidden'); } }); } // Event listeners for filters courseTypeFilter.addEventListener('change', applyFilters); timeFilter.addEventListener('change', applyFilters); searchFilter.addEventListener('input', applyFilters); // Add smooth scrolling for anchor links document.querySelectorAll('a[href^=\" \"]').forEach(anchor => { anchor.addEventListener('click', function (e) { e.preventDefault(); const target = document.querySelector(this.getAttribute('href')); if (target) { target.scrollIntoView({ behavior: 'smooth', block: 'start' }); } }); }); });   Teaching /assets/js/teaching-page.js index .md","url":"/teaching/","category":"teaching","description":"","tags":"","semester":"","instructor":"","course_type":""},{"id":"teaching-Kompatible Systeme von Galoisdarstellungen","title":"Kompatible Systeme von Galoisdarstellungen","content":"Kompatible Systeme von Galoisdarstellungen Course Description Lecture on compatible systems of Galois representations and their applications. Course Information - Type: Vorlesung - Language: German/English - Credits: Varies by course type - Prerequisites: Basic knowledge in algebra and number theory (varies by course) Course Content This course covers lecture on compatible systems of galois representations and their applications. Learning Objectives Students will gain: - Deep understanding of kompatible systeme von galoisdarstellungen - Practical skills in mathematical reasoning and proof techniques - Experience with current research topics in the field - Ability to present mathematical concepts clearly Assessment Assessment methods vary by course type: - Vorlesung (Lecture): Written examination - Seminar: Oral presentation and participation - Proseminar: Oral presentation and written report - Hauptseminar: Advanced oral presentation and research component Materials Course materials will be provided during the semester, including: - Lecture notes and handouts - Recommended reading lists - Problem sets and exercises - Additional resources and references Related Courses This course is part of the Arithmetic Geometry research group's teaching program. Related courses include: - Algebraic Number Theory - Galois Representations - Arithmetic Geometry - Modular Forms --- Course information extracted from the original Heidelberg University teaching program Last updated: 2025-08-02   Vorlesung Kompatible Systeme von Galoisdarstellungen - Course information and materials. Prof. Dr. BÃ¶ckle, Dr. Conti en Summer term 2019 Kompatible Systeme von Galoisdarstellungen kompatible-systeme-von-galoisdarstellungen .md","url":"/teaching/kompatible-systeme-von-galoisdarstellungen/","category":"teaching","description":"Kompatible Systeme von Galoisdarstellungen - Course information and materials.","tags":"","semester":"Summer term 2019","instructor":"Prof. Dr. BÃ¶ckle, Dr. Conti","course_type":"Vorlesung"},{"id":"teaching-Modularity Lifting","title":"Modularity Lifting","content":"Modularity Lifting Course Description Main seminar on modularity lifting theorems. Course Information - Type: Hauptseminar - Language: German/English - Credits: Varies by course type - Prerequisites: Basic knowledge in algebra and number theory (varies by course) Course Content This course covers main seminar on modularity lifting theorems. Learning Objectives Students will gain: - Deep understanding of modularity lifting - Practical skills in mathematical reasoning and proof techniques - Experience with current research topics in the field - Ability to present mathematical concepts clearly Assessment Assessment methods vary by course type: - Vorlesung (Lecture): Written examination - Seminar: Oral presentation and participation - Proseminar: Oral presentation and written report - Hauptseminar: Advanced oral presentation and research component Materials Course materials will be provided during the semester, including: - Lecture notes and handouts - Recommended reading lists - Problem sets and exercises - Additional resources and references Related Courses This course is part of the Arithmetic Geometry research group's teaching program. Related courses include: - Algebraic Number Theory - Galois Representations - Arithmetic Geometry - Modular Forms --- Course information extracted from the original Heidelberg University teaching program Last updated: 2025-08-02   Hauptseminar Modularity Lifting - Course information and materials. Prof. Dr. BÃ¶ckle, Dr. CerviÃ±o, Fischer en Winter term 2013/14 Modularity Lifting mls-ws13 .md","url":"/teaching/mls-ws13/","category":"teaching","description":"Modularity Lifting - Course information and materials.","tags":"","semester":"Winter term 2013/14","instructor":"Prof. Dr. BÃ¶ckle, Dr. CerviÃ±o, Fischer","course_type":"Hauptseminar"},{"id":"teaching-Modularity and Galois Representations","title":"Modularity and Galois Representations","content":"Modularity and Galois Representations Course Description Advanced lecture on modularity theorems and their connections to Galois representations. Course Information - Type: Vorlesung - Language: German/English - Credits: Varies by course type - Prerequisites: Basic knowledge in algebra and number theory (varies by course) Course Content This course covers advanced lecture on modularity theorems and their connections to galois representations. Learning Objectives Students will gain: - Deep understanding of modularity and galois representations - Practical skills in mathematical reasoning and proof techniques - Experience with current research topics in the field - Ability to present mathematical concepts clearly Assessment Assessment methods vary by course type: - Vorlesung (Lecture): Written examination - Seminar: Oral presentation and participation - Proseminar: Oral presentation and written report - Hauptseminar: Advanced oral presentation and research component Materials Course materials will be provided during the semester, including: - Lecture notes and handouts - Recommended reading lists - Problem sets and exercises - Additional resources and references Related Courses This course is part of the Arithmetic Geometry research group's teaching program. Related courses include: - Algebraic Number Theory - Galois Representations - Arithmetic Geometry - Modular Forms --- Course information extracted from the original Heidelberg University teaching program Last updated: 2025-08-02   Vorlesung Modularity and Galois Representations - Course information and materials. Prof. Dr. BÃ¶ckle, Shavali en Winter term 2024/25 Modularity and Galois Representations modularity-and-galois-representations .md","url":"/teaching/modularity-and-galois-representations/","category":"teaching","description":"Modularity and Galois Representations - Course information and materials.","tags":"","semester":"Winter term 2024/25","instructor":"Prof. Dr. BÃ¶ckle, Shavali","course_type":"Vorlesung"},{"id":"teaching-p-adic numbers","title":"p-adic numbers","content":"p-adic numbers Course Description Proseminar on p-adic numbers, their properties, and applications in number theory and analysis. Course Information - Type: Proseminar - Language: German/English - Credits: Varies by course type - Prerequisites: Basic knowledge in algebra and number theory (varies by course) Course Content This course covers proseminar on p-adic numbers, their properties, and applications in number theory and analysis. Learning Objectives Students will gain: - Deep understanding of p-adic numbers - Practical skills in mathematical reasoning and proof techniques - Experience with current research topics in the field - Ability to present mathematical concepts clearly Assessment Assessment methods vary by course type: - Vorlesung (Lecture): Written examination - Seminar: Oral presentation and participation - Proseminar: Oral presentation and written report - Hauptseminar: Advanced oral presentation and research component Materials Course materials will be provided during the semester, including: - Lecture notes and handouts - Recommended reading lists - Problem sets and exercises - Additional resources and references Related Courses This course is part of the Arithmetic Geometry research group's teaching program. Related courses include: - Algebraic Number Theory - Galois Representations - Arithmetic Geometry - Modular Forms --- Course information extracted from the original Heidelberg University teaching program Last updated: 2025-08-02   Proseminar p-adic numbers - Course information and materials. Dr. BÃ¶ckle, C. V. Sriram en Summer term 2023 p-adic numbers p-adic-numbers .md","url":"/teaching/p-adic-numbers/","category":"teaching","description":"p-adic numbers - Course information and materials.","tags":"","semester":"Summer term 2023","instructor":"Dr. BÃ¶ckle, C. V. Sriram","course_type":"Proseminar"},{"id":"teaching-p-adic Uniformization","title":"p-adic Uniformization","content":"p-adic Uniformization Course Description Main seminar on p-adic uniformization theory. Course Information - Type: Hauptseminar - Language: German/English - Credits: Varies by course type - Prerequisites: Basic knowledge in algebra and number theory (varies by course) Course Content This course covers main seminar on p-adic uniformization theory. Learning Objectives Students will gain: - Deep understanding of p-adic uniformization - Practical skills in mathematical reasoning and proof techniques - Experience with current research topics in the field - Ability to present mathematical concepts clearly Assessment Assessment methods vary by course type: - Vorlesung (Lecture): Written examination - Seminar: Oral presentation and participation - Proseminar: Oral presentation and written report - Hauptseminar: Advanced oral presentation and research component Materials Course materials will be provided during the semester, including: - Lecture notes and handouts - Recommended reading lists - Problem sets and exercises - Additional resources and references Related Courses This course is part of the Arithmetic Geometry research group's teaching program. Related courses include: - Algebraic Number Theory - Galois Representations - Arithmetic Geometry - Modular Forms --- Course information extracted from the original Heidelberg University teaching program Last updated: 2025-08-02   Hauptseminar p-adic Uniformization - Course information and materials. Prof. Dr. BÃ¶ckle, Dr. Guiraud, Fischer, GrÃ¤f en Summer term 2016 p-adic Uniformization p-adic-uniformization-ss16 .md","url":"/teaching/p-adic-uniformization-ss16/","category":"teaching","description":"p-adic Uniformization - Course information and materials.","tags":"","semester":"Summer term 2016","instructor":"Prof. Dr. BÃ¶ckle, Dr. Guiraud, Fischer, GrÃ¤f","course_type":"Hauptseminar"},{"id":"teaching-p-divisible Gruppen","title":"p-divisible Gruppen","content":"p-divisible Gruppen Course Description Lecture on p-divisible groups and their role in arithmetic geometry. Course Information - Type: Vorlesung - Language: German/English - Credits: Varies by course type - Prerequisites: Basic knowledge in algebra and number theory (varies by course) Course Content This course covers lecture on p-divisible groups and their role in arithmetic geometry. Learning Objectives Students will gain: - Deep understanding of p-divisible gruppen - Practical skills in mathematical reasoning and proof techniques - Experience with current research topics in the field - Ability to present mathematical concepts clearly Assessment Assessment methods vary by course type: - Vorlesung (Lecture): Written examination - Seminar: Oral presentation and participation - Proseminar: Oral presentation and written report - Hauptseminar: Advanced oral presentation and research component Materials Course materials will be provided during the semester, including: - Lecture notes and handouts - Recommended reading lists - Problem sets and exercises - Additional resources and references Related Courses This course is part of the Arithmetic Geometry research group's teaching program. Related courses include: - Algebraic Number Theory - Galois Representations - Arithmetic Geometry - Modular Forms --- Course information extracted from the original Heidelberg University teaching program Last updated: 2025-08-02   Vorlesung p-divisible Gruppen - Course information and materials. Dr. Ludwig en Summer term 2019 p-divisible Gruppen p-divisible-gruppen .md","url":"/teaching/p-divisible-gruppen/","category":"teaching","description":"p-divisible Gruppen - Course information and materials.","tags":"","semester":"Summer term 2019","instructor":"Dr. Ludwig","course_type":"Vorlesung"},{"id":"teaching-Past Teaching at the University Duisburg-Essen","title":"Past Teaching at the University Duisburg-Essen","content":"Past Teaching at the University Duisburg-Essen This page contains information about teaching activities at the University Duisburg-Essen before joining Heidelberg University. Courses Taught Note: This section will be populated with historical teaching information from the University Duisburg-Essen. Research Seminars Note: This section will contain information about research seminars conducted at the University Duisburg-Essen. Student Supervision Note: This section will list supervised students and their thesis topics from the University Duisburg-Essen period. --- For current teaching activities, please see the main Teaching page.   seminar Past Teaching at the University Duisburg-Essen - Course information and materials. Unknown en Unknown Past Teaching at the University Duisburg-Essen past-teaching .md","url":"/teaching/past-teaching/","category":"teaching","description":"Past Teaching at the University Duisburg-Essen - Course information and materials.","tags":"","semester":"Unknown","instructor":"Unknown","course_type":"seminar"},{"id":"teaching-Prime numbers and Cryptography","title":"Prime numbers and Cryptography","content":"Prime numbers and Cryptography Course Description Proseminar on the interplay between prime numbers and modern cryptography. Course Information - Type: Proseminar - Language: German/English - Credits: Varies by course type - Prerequisites: Basic knowledge in algebra and number theory (varies by course) Course Content This course covers proseminar on the interplay between prime numbers and modern cryptography. Learning Objectives Students will gain: - Deep understanding of prime numbers and cryptography - Practical skills in mathematical reasoning and proof techniques - Experience with current research topics in the field - Ability to present mathematical concepts clearly Assessment Assessment methods vary by course type: - Vorlesung (Lecture): Written examination - Seminar: Oral presentation and participation - Proseminar: Oral presentation and written report - Hauptseminar: Advanced oral presentation and research component Materials Course materials will be provided during the semester, including: - Lecture notes and handouts - Recommended reading lists - Problem sets and exercises - Additional resources and references Related Courses This course is part of the Arithmetic Geometry research group's teaching program. Related courses include: - Algebraic Number Theory - Galois Representations - Arithmetic Geometry - Modular Forms --- Course information extracted from the original Heidelberg University teaching program Last updated: 2025-08-02   Proseminar Prime numbers and Cryptography - Course information and materials. Dr. Banwait, C. V. Sriram en Summer term 2022 Prime numbers and Cryptography prime-numbers-and-cryptography-proseminar .md","url":"/teaching/prime-numbers-and-cryptography-proseminar/","category":"teaching","description":"Prime numbers and Cryptography - Course information and materials.","tags":"","semester":"Summer term 2022","instructor":"Dr. Banwait, C. V. Sriram","course_type":"Proseminar"},{"id":"teaching-Bilinearformen und klassische Gruppen","title":"Bilinearformen und klassische Gruppen","content":"Bilinearformen und klassische Gruppen Course Description Proseminar on bilinear forms and classical groups. Course Information - Type: Proseminar - Language: German/English - Credits: Varies by course type - Prerequisites: Basic knowledge in algebra and number theory (varies by course) Course Content This course covers proseminar on bilinear forms and classical groups. Learning Objectives Students will gain: - Deep understanding of bilinearformen und klassische gruppen - Practical skills in mathematical reasoning and proof techniques - Experience with current research topics in the field - Ability to present mathematical concepts clearly Assessment Assessment methods vary by course type: - Vorlesung (Lecture): Written examination - Seminar: Oral presentation and participation - Proseminar: Oral presentation and written report - Hauptseminar: Advanced oral presentation and research component Materials Course materials will be provided during the semester, including: - Lecture notes and handouts - Recommended reading lists - Problem sets and exercises - Additional resources and references Related Courses This course is part of the Arithmetic Geometry research group's teaching program. Related courses include: - Algebraic Number Theory - Galois Representations - Arithmetic Geometry - Modular Forms --- Course information extracted from the original Heidelberg University teaching program Last updated: 2025-08-02   Proseminar Bilinearformen und klassische Gruppen - Course information and materials. Prof. Dr. BÃ¶ckle, Quast en Summer term 2019 Bilinearformen und klassische Gruppen proseminar-bilinearformen-und-klassische-gruppen .md","url":"/teaching/proseminar-bilinearformen-und-klassische-gruppen/","category":"teaching","description":"Bilinearformen und klassische Gruppen - Course information and materials.","tags":"","semester":"Summer term 2019","instructor":"Prof. Dr. BÃ¶ckle, Quast","course_type":"Proseminar"},{"id":"teaching-Primzahlen und Faktorisierung fÃ¼r die Kryptographie","title":"Primzahlen und Faktorisierung fÃ¼r die Kryptographie","content":"Primzahlen und Faktorisierung fÃ¼r die Kryptographie Course Description Proseminar on prime numbers and factorization methods in cryptography. Course Information - Type: Proseminar - Language: German/English - Credits: Varies by course type - Prerequisites: Basic knowledge in algebra and number theory (varies by course) Course Content This course covers proseminar on prime numbers and factorization methods in cryptography. Learning Objectives Students will gain: - Deep understanding of primzahlen und faktorisierung fÃ¼r die kryptographie - Practical skills in mathematical reasoning and proof techniques - Experience with current research topics in the field - Ability to present mathematical concepts clearly Assessment Assessment methods vary by course type: - Vorlesung (Lecture): Written examination - Seminar: Oral presentation and participation - Proseminar: Oral presentation and written report - Hauptseminar: Advanced oral presentation and research component Materials Course materials will be provided during the semester, including: - Lecture notes and handouts - Recommended reading lists - Problem sets and exercises - Additional resources and references Related Courses This course is part of the Arithmetic Geometry research group's teaching program. Related courses include: - Algebraic Number Theory - Galois Representations - Arithmetic Geometry - Modular Forms --- Course information extracted from the original Heidelberg University teaching program Last updated: 2025-08-02   Proseminar Primzahlen und Faktorisierung fÃ¼r die Kryptographie - Course information and materials. Prof. Dr. BÃ¶ckle, Fischer en Winter term 2016/17 Primzahlen und Faktorisierung fÃ¼r die Kryptographie proseminar-primzahlen-und-faktorisierung .md","url":"/teaching/proseminar-primzahlen-und-faktorisierung/","category":"teaching","description":"Primzahlen und Faktorisierung fÃ¼r die Kryptographie - Course information and materials.","tags":"","semester":"Winter term 2016/17","instructor":"Prof. Dr. BÃ¶ckle, Fischer","course_type":"Proseminar"},{"id":"teaching-p-adische Analysis","title":"p-adische Analysis","content":"p-adische Analysis Course Description Proseminar on p-adic analysis and its applications. Course Information - Type: Proseminar - Language: German/English - Credits: Varies by course type - Prerequisites: Basic knowledge in algebra and number theory (varies by course) Course Content This course covers proseminar on p-adic analysis and its applications. Learning Objectives Students will gain: - Deep understanding of p-adische analysis - Practical skills in mathematical reasoning and proof techniques - Experience with current research topics in the field - Ability to present mathematical concepts clearly Assessment Assessment methods vary by course type: - Vorlesung (Lecture): Written examination - Seminar: Oral presentation and participation - Proseminar: Oral presentation and written report - Hauptseminar: Advanced oral presentation and research component Materials Course materials will be provided during the semester, including: - Lecture notes and handouts - Recommended reading lists - Problem sets and exercises - Additional resources and references Related Courses This course is part of the Arithmetic Geometry research group's teaching program. Related courses include: - Algebraic Number Theory - Galois Representations - Arithmetic Geometry - Modular Forms --- Course information extracted from the original Heidelberg University teaching program Last updated: 2025-08-02   Proseminar p-adische Analysis - Course information and materials. Prof. Dr. BÃ¶ckle, GrÃ¤f en Summer term 2016 p-adische Analysis proseminar .md","url":"/teaching/proseminar/","category":"teaching","description":"p-adische Analysis - Course information and materials.","tags":"","semester":"Summer term 2016","instructor":"Prof. Dr. BÃ¶ckle, GrÃ¤f","course_type":"Proseminar"},{"id":"teaching-Quadratic forms","title":"Quadratic forms","content":"Quadratic forms Course Description Proseminar on quadratic forms, covering their classification, properties, and applications in number theory. Course Information - Type: Proseminar - Language: German/English - Credits: Varies by course type - Prerequisites: Basic knowledge in algebra and number theory (varies by course) Course Content This course covers proseminar on quadratic forms, covering their classification, properties, and applications in number theory. Learning Objectives Students will gain: - Deep understanding of quadratic forms - Practical skills in mathematical reasoning and proof techniques - Experience with current research topics in the field - Ability to present mathematical concepts clearly Assessment Assessment methods vary by course type: - Vorlesung (Lecture): Written examination - Seminar: Oral presentation and participation - Proseminar: Oral presentation and written report - Hauptseminar: Advanced oral presentation and research component Materials Course materials will be provided during the semester, including: - Lecture notes and handouts - Recommended reading lists - Problem sets and exercises - Additional resources and references Related Courses This course is part of the Arithmetic Geometry research group's teaching program. Related courses include: - Algebraic Number Theory - Galois Representations - Arithmetic Geometry - Modular Forms --- Course information extracted from the original Heidelberg University teaching program Last updated: 2025-08-02   Proseminar Quadratic forms - Course information and materials. Prof. Dr. BÃ¶ckle, C.V. Sriram en Winter term 2023/24 Quadratic forms quadratic-forms .md","url":"/teaching/quadratic-forms/","category":"teaching","description":"Quadratic forms - Course information and materials.","tags":"","semester":"Winter term 2023/24","instructor":"Prof. Dr. BÃ¶ckle, C.V. Sriram","course_type":"Proseminar"},{"id":"teaching-Affine algebraische Gruppen","title":"Affine algebraische Gruppen","content":"Affine algebraische Gruppen Course Description Seminar on affine algebraic groups and their representation theory. Course Information - Type: Seminar - Language: German/English - Credits: Varies by course type - Prerequisites: Basic knowledge in algebra and number theory (varies by course) Course Content This course covers seminar on affine algebraic groups and their representation theory. Learning Objectives Students will gain: - Deep understanding of affine algebraische gruppen - Practical skills in mathematical reasoning and proof techniques - Experience with current research topics in the field - Ability to present mathematical concepts clearly Assessment Assessment methods vary by course type: - Vorlesung (Lecture): Written examination - Seminar: Oral presentation and participation - Proseminar: Oral presentation and written report - Hauptseminar: Advanced oral presentation and research component Materials Course materials will be provided during the semester, including: - Lecture notes and handouts - Recommended reading lists - Problem sets and exercises - Additional resources and references Related Courses This course is part of the Arithmetic Geometry research group's teaching program. Related courses include: - Algebraic Number Theory - Galois Representations - Arithmetic Geometry - Modular Forms --- Course information extracted from the original Heidelberg University teaching program Last updated: 2025-08-02   Seminar Affine algebraische Gruppen - Course information and materials. Prof. Dr. BÃ¶ckle, Quast en Winter term 2019/20 Affine algebraische Gruppen seminar-affine-algebraische-gruppen .md","url":"/teaching/seminar-affine-algebraische-gruppen/","category":"teaching","description":"Affine algebraische Gruppen - Course information and materials.","tags":"","semester":"Winter term 2019/20","instructor":"Prof. Dr. BÃ¶ckle, Quast","course_type":"Seminar"},{"id":"teaching-Algorithmische Algebra","title":"Algorithmische Algebra","content":"Algorithmische Algebra Course Description Seminar on algorithmic algebra and computational methods in algebra. Course Information - Type: Seminar - Language: German/English - Credits: Varies by course type - Prerequisites: Basic knowledge in algebra and number theory (varies by course) Course Content This course covers seminar on algorithmic algebra and computational methods in algebra. Learning Objectives Students will gain: - Deep understanding of algorithmische algebra - Practical skills in mathematical reasoning and proof techniques - Experience with current research topics in the field - Ability to present mathematical concepts clearly Assessment Assessment methods vary by course type: - Vorlesung (Lecture): Written examination - Seminar: Oral presentation and participation - Proseminar: Oral presentation and written report - Hauptseminar: Advanced oral presentation and research component Materials Course materials will be provided during the semester, including: - Lecture notes and handouts - Recommended reading lists - Problem sets and exercises - Additional resources and references Related Courses This course is part of the Arithmetic Geometry research group's teaching program. Related courses include: - Algebraic Number Theory - Galois Representations - Arithmetic Geometry - Modular Forms --- Course information extracted from the original Heidelberg University teaching program Last updated: 2025-08-02   Seminar Algorithmische Algebra - Course information and materials. Dr. Maurischat en Winter term 2018/19 Algorithmische Algebra seminar-algorithmische-algebra .md","url":"/teaching/seminar-algorithmische-algebra/","category":"teaching","description":"Algorithmische Algebra - Course information and materials.","tags":"","semester":"Winter term 2018/19","instructor":"Dr. Maurischat","course_type":"Seminar"},{"id":"teaching-Elliptische Kurven","title":"Elliptische Kurven","content":"Elliptische Kurven Course Description Seminar on elliptic curves, their arithmetic, and applications in cryptography. Course Information - Type: Seminar - Language: German/English - Credits: Varies by course type - Prerequisites: Basic knowledge in algebra and number theory (varies by course) Course Content This course covers seminar on elliptic curves, their arithmetic, and applications in cryptography. Learning Objectives Students will gain: - Deep understanding of elliptische kurven - Practical skills in mathematical reasoning and proof techniques - Experience with current research topics in the field - Ability to present mathematical concepts clearly Assessment Assessment methods vary by course type: - Vorlesung (Lecture): Written examination - Seminar: Oral presentation and participation - Proseminar: Oral presentation and written report - Hauptseminar: Advanced oral presentation and research component Materials Course materials will be provided during the semester, including: - Lecture notes and handouts - Recommended reading lists - Problem sets and exercises - Additional resources and references Related Courses This course is part of the Arithmetic Geometry research group's teaching program. Related courses include: - Algebraic Number Theory - Galois Representations - Arithmetic Geometry - Modular Forms --- Course information extracted from the original Heidelberg University teaching program Last updated: 2025-08-02   Seminar Elliptische Kurven - Course information and materials. Prof. Dr. BÃ¶ckle, Dr. Ludwig en Winter term 2020/21 Elliptische Kurven seminar-elliptische-kurven .md","url":"/teaching/seminar-elliptische-kurven/","category":"teaching","description":"Elliptische Kurven - Course information and materials.","tags":"","semester":"Winter term 2020/21","instructor":"Prof. Dr. BÃ¶ckle, Dr. Ludwig","course_type":"Seminar"},{"id":"teaching-Gruppenkohomologie","title":"Gruppenkohomologie","content":"Gruppenkohomologie Course Description Seminar on group cohomology and its applications. Course Information - Type: Seminar - Language: German/English - Credits: Varies by course type - Prerequisites: Basic knowledge in algebra and number theory (varies by course) Course Content This course covers seminar on group cohomology and its applications. Learning Objectives Students will gain: - Deep understanding of gruppenkohomologie - Practical skills in mathematical reasoning and proof techniques - Experience with current research topics in the field - Ability to present mathematical concepts clearly Assessment Assessment methods vary by course type: - Vorlesung (Lecture): Written examination - Seminar: Oral presentation and participation - Proseminar: Oral presentation and written report - Hauptseminar: Advanced oral presentation and research component Materials Course materials will be provided during the semester, including: - Lecture notes and handouts - Recommended reading lists - Problem sets and exercises - Additional resources and references Related Courses This course is part of the Arithmetic Geometry research group's teaching program. Related courses include: - Algebraic Number Theory - Galois Representations - Arithmetic Geometry - Modular Forms --- Course information extracted from the original Heidelberg University teaching program Last updated: 2025-08-02   Seminar Gruppenkohomologie - Course information and materials. Prof. Dr. BÃ¶ckle, Fischer en Winter term 2017/18 Gruppenkohomologie seminar-gruppenkohomologie .md","url":"/teaching/seminar-gruppenkohomologie/","category":"teaching","description":"Gruppenkohomologie - Course information and materials.","tags":"","semester":"Winter term 2017/18","instructor":"Prof. Dr. BÃ¶ckle, Fischer","course_type":"Seminar"},{"id":"teaching-Lokale KlassenkÃ¶rpertheorie nach Lubin-Tate","title":"Lokale KlassenkÃ¶rpertheorie nach Lubin-Tate","content":"Lokale KlassenkÃ¶rpertheorie nach Lubin-Tate Course Description Seminar on local class field theory using the Lubin-Tate approach. Course Information - Type: Seminar - Language: German/English - Credits: Varies by course type - Prerequisites: Basic knowledge in algebra and number theory (varies by course) Course Content This course covers seminar on local class field theory using the lubin-tate approach. Learning Objectives Students will gain: - Deep understanding of lokale klassenkÃ¶rpertheorie nach lubin-tate - Practical skills in mathematical reasoning and proof techniques - Experience with current research topics in the field - Ability to present mathematical concepts clearly Assessment Assessment methods vary by course type: - Vorlesung (Lecture): Written examination - Seminar: Oral presentation and participation - Proseminar: Oral presentation and written report - Hauptseminar: Advanced oral presentation and research component Materials Course materials will be provided during the semester, including: - Lecture notes and handouts - Recommended reading lists - Problem sets and exercises - Additional resources and references Related Courses This course is part of the Arithmetic Geometry research group's teaching program. Related courses include: - Algebraic Number Theory - Galois Representations - Arithmetic Geometry - Modular Forms --- Course information extracted from the original Heidelberg University teaching program Last updated: 2025-08-02   Seminar Lokale KlassenkÃ¶rpertheorie nach Lubin-Tate - Course information and materials. Prof. Dr. BÃ¶ckle, Fischer en Summer term 2018 Lokale KlassenkÃ¶rpertheorie nach Lubin-Tate seminar-lubin-tate-theorie .md","url":"/teaching/seminar-lubin-tate-theorie/","category":"teaching","description":"Lokale KlassenkÃ¶rpertheorie nach Lubin-Tate - Course information and materials.","tags":"","semester":"Summer term 2018","instructor":"Prof. Dr. BÃ¶ckle, Fischer","course_type":"Seminar"},{"id":"teaching-Representation theory of finite groups","title":"Representation theory of finite groups","content":"Course Description Seminar covering the representation theory of finite groups and its applications. Course Information - Type: Seminar - Language: German/English - Credits: Varies by course type - Prerequisites: Basic knowledge in algebra and number theory (varies by course) Course Content This course covers seminar covering the representation theory of finite groups and its applications. Learning Objectives Students will gain: - Deep understanding of representation theory of finite groups - Practical skills in mathematical reasoning and proof techniques - Experience with current research topics in the field - Ability to present mathematical concepts clearly Assessment Assessment methods vary by course type: - Vorlesung (Lecture): Written examination - Seminar: Oral presentation and participation - Proseminar: Oral presentation and written report - Hauptseminar: Advanced oral presentation and research component Materials Course materials will be provided during the semester, including: - Lecture notes and handouts - Recommended reading lists - Problem sets and exercises - Additional resources and references Contact Information Primary Instructor: {{ page.instructors | default: 'Contact department' }} Email: arithgeo@iwr.uni-heidelberg.de Office Hours: By appointment  Seminar Seminar covering the representation theory of finite groups and its applications. Prof. Dr. BÃ¶ckle, Chilla, Dr. GezmiÅ en Summer term 2024 Representation theory of finite groups seminar-on-representation-theory-of-finite-groups-summer-semester-2024 .md","url":"/teaching/seminar-on-representation-theory-of-finite-groups-summer-semester-2024/","category":"teaching","description":"Seminar covering the representation theory of finite groups and its applications.","tags":"","semester":"Summer term 2024","instructor":"Prof. Dr. BÃ¶ckle, Chilla, Dr. GezmiÅ","course_type":"Seminar"},{"id":"teaching-p-adische Geometrie","title":"p-adische Geometrie","content":"p-adische Geometrie Course Description Seminar on p-adic geometry and its applications. Course Information - Type: Seminar - Language: German/English - Credits: Varies by course type - Prerequisites: Basic knowledge in algebra and number theory (varies by course) Course Content This course covers seminar on p-adic geometry and its applications. Learning Objectives Students will gain: - Deep understanding of p-adische geometrie - Practical skills in mathematical reasoning and proof techniques - Experience with current research topics in the field - Ability to present mathematical concepts clearly Assessment Assessment methods vary by course type: - Vorlesung (Lecture): Written examination - Seminar: Oral presentation and participation - Proseminar: Oral presentation and written report - Hauptseminar: Advanced oral presentation and research component Materials Course materials will be provided during the semester, including: - Lecture notes and handouts - Recommended reading lists - Problem sets and exercises - Additional resources and references Related Courses This course is part of the Arithmetic Geometry research group's teaching program. Related courses include: - Algebraic Number Theory - Galois Representations - Arithmetic Geometry - Modular Forms --- Course information extracted from the original Heidelberg University teaching program Last updated: 2025-08-02   Seminar p-adische Geometrie - Course information and materials. Prof. Dr. BÃ¶ckle, Juschka, Qiu en Summer term 2014 p-adische Geometrie seminar-ss2014 .md","url":"/teaching/seminar-ss2014/","category":"teaching","description":"p-adische Geometrie - Course information and materials.","tags":"","semester":"Summer term 2014","instructor":"Prof. Dr. BÃ¶ckle, Juschka, Qiu","course_type":"Seminar"},{"id":"teaching-Deformationen von (Pseudo-)Darstellungen","title":"Deformationen von (Pseudo-)Darstellungen","content":"Deformationen von (Pseudo-)Darstellungen Course Description Seminar on deformations of (pseudo-)representations. Course Information - Type: Seminar - Language: German/English - Credits: Varies by course type - Prerequisites: Basic knowledge in algebra and number theory (varies by course) Course Content This course covers seminar on deformations of (pseudo-)representations. Learning Objectives Students will gain: - Deep understanding of deformationen von (pseudo-)darstellungen - Practical skills in mathematical reasoning and proof techniques - Experience with current research topics in the field - Ability to present mathematical concepts clearly Assessment Assessment methods vary by course type: - Vorlesung (Lecture): Written examination - Seminar: Oral presentation and participation - Proseminar: Oral presentation and written report - Hauptseminar: Advanced oral presentation and research component Materials Course materials will be provided during the semester, including: - Lecture notes and handouts - Recommended reading lists - Problem sets and exercises - Additional resources and references Related Courses This course is part of the Arithmetic Geometry research group's teaching program. Related courses include: - Algebraic Number Theory - Galois Representations - Arithmetic Geometry - Modular Forms --- Course information extracted from the original Heidelberg University teaching program Last updated: 2025-08-02   Seminar Deformationen von (Pseudo-)Darstellungen - Course information and materials. Prof. Dr. BÃ¶ckle, Juschka en Winter term 2013/14 Deformationen von (Pseudo-)Darstellungen seminar-ws2013 .md","url":"/teaching/seminar-ws2013/","category":"teaching","description":"Deformationen von (Pseudo-)Darstellungen - Course information and materials.","tags":"","semester":"Winter term 2013/14","instructor":"Prof. Dr. BÃ¶ckle, Juschka","course_type":"Seminar"},{"id":"teaching-Torische VarietÃ¤ten","title":"Torische VarietÃ¤ten","content":"Torische VarietÃ¤ten Course Description Seminar on toric varieties and their applications. Course Information - Type: Seminar - Language: German/English - Credits: Varies by course type - Prerequisites: Basic knowledge in algebra and number theory (varies by course) Course Content This course covers seminar on toric varieties and their applications. Learning Objectives Students will gain: - Deep understanding of torische varietÃ¤ten - Practical skills in mathematical reasoning and proof techniques - Experience with current research topics in the field - Ability to present mathematical concepts clearly Assessment Assessment methods vary by course type: - Vorlesung (Lecture): Written examination - Seminar: Oral presentation and participation - Proseminar: Oral presentation and written report - Hauptseminar: Advanced oral presentation and research component Materials Course materials will be provided during the semester, including: - Lecture notes and handouts - Recommended reading lists - Problem sets and exercises - Additional resources and references Related Courses This course is part of the Arithmetic Geometry research group's teaching program. Related courses include: - Algebraic Number Theory - Galois Representations - Arithmetic Geometry - Modular Forms --- Course information extracted from the original Heidelberg University teaching program Last updated: 2025-08-02   Seminar Torische VarietÃ¤ten - Course information and materials. Prof. Dr. BÃ¶ckle en Summer term 2013 Torische VarietÃ¤ten toric-ss13 .md","url":"/teaching/toric-ss13/","category":"teaching","description":"Torische VarietÃ¤ten - Course information and materials.","tags":"","semester":"Summer term 2013","instructor":"Prof. Dr. BÃ¶ckle","course_type":"Seminar"}]